Workbook

Sheet Product Hierarchy
A1: L5 SKU | B1: L5 Part # | C1: Brand | D1: DESCRIPTION | E1: Product Group | F1: Product Type
A2: DXTT-3-730 | B2: 3-730 | C2: DEWALT | D2: DEWALT 16 x 3 1/8" Mag Float | E2: Concrete Hand Tools | F2: Concrete Floats
A3: DXTT-3-731 | B3: 3-731 | C3: DEWALT | D3: DEWALT 15.5" x 3" Extruded Aluminum Float | E3: Concrete Hand Tools | F3: Concrete Floats
A4: 5-730 | B4: 5-730 | C4: LEVEL5 | D4: 15.5" x 3" Extruded Aluminum Float | E4: Concrete Hand Tools | F4: Concrete Floats
A5: 5-731 | B5: 5-731 | C5: LEVEL5 | D5: 16" x 3 1/8" Extruded Magnesium Float | E5: Concrete Hand Tools | F5: Concrete Floats
A6: 5-920 | B6: 5-920 | C6: LEVEL5 | D6: 9" x 4" Black Rubber Float; Composite Hndl | E6: Concrete Hand Tools | F6: Concrete Floats
A7: 5-921 | B7: 5-921 | C7: LEVEL5 | D7: 9" x 4" Red Rubber Float; Composite Hndl | E7: Concrete Hand Tools | F7: Concrete Floats
A8: 5-925 | B8: 5-925 | C8: LEVEL5 | D8: 6" x 2" Margin Float | E8: Concrete Hand Tools | F8: Concrete Floats
A9: DXTT-3-744 | B9: 3-744 | C9: DEWALT | D9: DEWALT 6" x 3" Stainless Steel Edger | E9: Concrete Hand Tools | F9: Edgers
A10: DXTT-3-745 | B10: 3-745 | C10: DEWALT | D10: DEWALT 6 x 4" SS Edger | E10: Concrete Hand Tools | F10: Edgers
A11: 5-740 | B11: 5-740 | C11: LEVEL5 | D11: 10" x 10" x 1/2" Walking Edger | E11: Concrete Hand Tools | F11: Edgers
A12: 5-743 | B12: 5-743 | C12: LEVEL5 | D12: 6" x 3" Concrete Edger | E12: Concrete Hand Tools | F12: Edgers
... A466: 4-748 | B466: 4-748 | C466: LEVEL5 | D466: 90° Outside Corner Applicator Head | E466: Drywall Auto Tools | F466: Outside Applicator Head
A467: 1142 | B467: 1142 | C467: DEWALT | D467: MudShot Nozzle Assembly | E467: Drywall Auto Tools | F467: Parts
A468: 1143 | B468: 1143 | C468: DEWALT | D468: DEWALT Double Threaded Mudshot Connector | E468: Drywall Auto Tools | F468: Parts
A469: 2166 | B469: 2166 | C469: DEWALT | D469: DEWALT Taper Tube | E469: Drywall Auto Tools | F469: Parts
A470: 2212 | B470: 2212 | C470: DEWALT | D470: DeWalt Ext Box Handle Head | E470: Drywall Auto Tools | F470: Parts
A471: 2-774R | B471: 2-774R | C471: DEWALT | D471: REFURB DEWALT MS Pressurized Applicator Tube | E471: Drywall Auto Tools | F471: Parts
A472: 9191DW | B472: 9191DW | C472: DEWALT | D472: Wrench -DeWalt Customer MCM-7122A14 | E472: Drywall Auto Tools | F472: Parts
A473: DXTT-1101 | B473: 1101 | C473: DEWALT | D473: Extension O'Ring | E473: Drywall Auto Tools | F473: Parts
A474: DXTT-1102 | B474: 1102 | C474: DEWALT | D474: Screw 8-32 x 6 | E474: Drywall Auto Tools | F474: Parts
A475: DXTT-1103 | B475: 1103 | C475: DEWALT | D475: Screw 8-32 x 9.4 | E475: Drywall Auto Tools | F475: Parts
A476: DXTT-1104 | B476: 1104 | C476: DEWALT | D476: Threaded Extension End | E476: Drywall Auto Tools | F476: Parts
A477: DXTT-1105 | B477: 1105 | C477: DEWALT | D477: Rubber Handle Grip | E477: Drywall Auto Tools | F477: Parts
A478: DXTT-1107 | B478: 1107 | C478: DEWALT | D478: Screw 6-32 x 7 | E478: Drywall Auto Tools | F478: Parts
A479: DXTT-1108 | B479: 1108 | C479: DEWALT | D479: Base | E479: Drywall Auto Tools | F479: Parts
A480: DXTT-1109 | B480: 1109 | C480: DEWALT | D480: MudShot U-Cup | E480: Drywall Auto Tools | F480: Parts
A481: DXTT-1110 | B481: 1110 | C481: DEWALT | D481: Screw 6-32 x 10.7 | E481: Drywall Auto Tools | F481: Parts
A482: DXTT-1111 | B482: 1111 | C482: DEWALT | D482: Clear Tube Base | E482: Drywall Auto Tools | F482: Parts
A483: DXTT-1112 | B483: 1112 | C483: DEWALT | D483: Top/Bottom Support Band | E483: Drywall Auto Tools | F483: Parts
A484: DXTT-1113 | B484: 1113 | C484: DEWALT | D484: Clear Tube | E484: Drywall Auto Tools | F484: Parts
... A531: DXTT-2719 | B531: 2719 | C531: DEWALT | D531: Black Box Wheel | E531: Drywall Auto Tools | F531: Parts
A532: DXTT-2-774 | B532: 2-774 | C532: DEWALT | D532: DEWALT MS Pressurized Applicator Tube | E532: Drywall Auto Tools | F532: Parts
A533: DXTT-2-801 | B533: 2-801 | C533: DEWALT | D533: DEWALT Pump Rebuild Kit | E533: Drywall Auto Tools | F533: Repair Kits
A534: DXTT-2-805 | B534: 2-805 | C534: DEWALT | D534: DEWALT 7"Flat Box Seal | E534: Drywall Auto Tools | F534: Parts
A535: DXTT-2-806 | B535: 2-806 | C535: DEWALT | D535: DEWALT 10"Flat Box Seal | E535: Drywall Auto Tools | F535: Parts
A536: DXTT-2-807 | B536: 2-807 | C536: DEWALT | D536: DEWALT 12"Flat Box Seal | E536: Drywall Auto Tools | F536: Parts
A537: DXTT-9685 | B537: 9685 | C537: DEWALT | D537: FB Box Tire | E537: Drywall Auto Tools | F537: Parts
A538: 1137 | B538: 1137 | C538: LEVEL5 | D538: MR Gas Cylinder | E538: Drywall Auto Tools | F538: Parts
A539: 7001 | B539: 7001 | C539: LEVEL5 | D539: Handle Outlet Valve | E539: Drywall Auto Tools | F539: Parts
A540: 7002 | B540: 7002 | C540: LEVEL5 | D540: Wiper, Control Valve | E540: Drywall Auto Tools | F540: Parts
A541: 7003 | B541: 7003 | C541: LEVEL5 | D541: Wiper Retainer | E541: Drywall Auto Tools | F541: Parts
A542: 7004 | B542: 7004 | C542: LEVEL5 | D542: 4-40 Hex Nut | E542: Drywall Auto Tools | F542: Parts
A543: 7005 | B543: 7005 | C543: LEVEL5 | D543: Lock Roller Assembly (Brake) | E543: Drywall Auto Tools | F543: Parts
A544: 7009 | B544: 7009 | C544: LEVEL5 | D544: 6-32 x 3/8 Fillister Screw SST | E544: Drywall Auto Tools | F544: Parts
A545: 7010 | B545: 7010 | C545: LEVEL5 | D545: 6-32 x 5/16 Round Head Screw | E545: Drywall Auto Tools | F545: Parts
A546: 7011 | B546: 7011 | C546: LEVEL5 | D546: 4-40 X 3/16 Truss Head Screw | E546: Drywall Auto Tools | F546: Parts
A547: 7012 | B547: 7012 | C547: LEVEL5 | D547: #6-32 x 1/4 Fillister Head | E547: Drywall Auto Tools | F547: Parts
A548: 7013 | B548: 7013 | C548: LEVEL5 | D548: #6 Lockwasher Medium | E548: Drywall Auto Tools | F548: Parts
A549: 7014 | B549: 7014 | C549: LEVEL5 | D549: Collar Bushing | E549: Drywall Auto Tools | F549: Parts
... A1221: 9999 | B1221: 9999 | C1221: LEVEL5 | D1221: AT Extension Arm Guide | E1221: Drywall Auto Tools | F1221: Parts
A1222: 4-774 | B1222: 4-774 | C1222: LEVEL5 | D1222: Clear Compound Tube | E1222: Drywall Auto Tools | F1222: Parts
A1223: 4-802 | B1223: 4-802 | C1223: LEVEL5 | D1223: Ext. Box Handle Brake Assembly | E1223: Drywall Auto Tools | F1223: Parts
A1224: 4-806 | B1224: 4-806 | C1224: LEVEL5 | D1224: 10"Flat Box Seal | E1224: Drywall Auto Tools | F1224: Parts
A1225: 4-811 | B1225: 4-811 | C1225: LEVEL5 | D1225: Cleaning Nozzles 2pk | E1225: Drywall Auto Tools | F1225: Parts
A1226: 4-812 | B1226: 4-812 | C1226: LEVEL5 | D1226: Tape Jam Remover | E1226: Drywall Auto Tools | F1226: Parts
A1227: 4-813 | B1227: 4-813 | C1227: LEVEL5 | D1227: Gooseneck Brush | E1227: Drywall Auto Tools | F1227: Parts
A1228: 4-817 | B1228: 4-817 | C1228: LEVEL5 | D1228: Gooser Assembly | E1228: Drywall Auto Tools | F1228: Parts
A1229: 4-818 | B1229: 4-818 | C1229: LEVEL5 | D1229: Drive Dog Assembly | E1229: Drywall Auto Tools | F1229: Parts
A1230: 4-821 | B1230: 4-821 | C1230: LEVEL5 | D1230: 10 Pack Pyramid Blades | E1230: Drywall Auto Tools | F1230: Parts
A1231: 4-822 | B1231: 4-822 | C1231: LEVEL5 | D1231: 25 Pack Pyramid Blades | E1231: Drywall Auto Tools | F1231: Parts
A1232: 4-823 | B1232: 4-823 | C1232: LEVEL5 | D1232: 10 Pack Pump Gaskets | E1232: Drywall Auto Tools | F1232: Parts
A1233: 4-824 | B1233: 4-824 | C1233: LEVEL5 | D1233: 10 Pack Filler O'Rings | E1233: Drywall Auto Tools | F1233: Parts
... A1253: 90101A007 | B1253: 90101A007 | C1253: LEVEL5 | D1253: 18-8 SS Thin Nylon-Insert Locknut, 6-32 Thread Size , 5/16" Wide, 1/8" High | E1253: Drywall Auto Tools | F1253: Parts
A1254: 9185(9815 is the correct part) | B1254: 9185 | C1254: LEVEL5 | D1254: CF 3.5" Blade | E1254: Drywall Auto Tools | F1254: Parts
A1255: 9191W | B1255: 9191W | C1255: LEVEL5 | D1255: Wrench for 9191 Fastenal 0257039 | E1255: Drywall Auto Tools | F1255: Parts
A1256: BN-5039 | B1256: BN-5039 | C1256: LEVEL5 | D1256: Nitrile/Nylon (SPEC 2550) .025 +/-.003" | E1256: Drywall Auto Tools | F1256: Parts
A1257: BN-5039 T | B1257: BN-5039 T | C1257: LEVEL5 | D1257: Nitrile/Nylon (SPEC 2551) .050 +/-.003" | E1257: Drywall Auto Tools | F1257: Parts
A1258: GSS 619526 | B1258: GSS 619526 | C1258: LEVEL5 | D1258: GS10-1550-061 without end fittings | E1258: Drywall Auto Tools | F1258: Parts
A1259: GSS 635791 | B1259: GSS 635791 | C1259: LEVEL5 | D1259: Gas Spring, 245MM Stroke, 560MM Ext Length, 350 Newtons | E1259: Drywall Auto Tools | F1259: Parts
A1260: DXTT-2-803 | B1260: 2-803 | C1260: DEWALT | D1260: DEWALT Taper/Gooseneck Cleaning Kit | E1260: Drywall Auto Tools | F1260: Repair Kits
A1261: 4-800 | B1261: 4-800 | C1261: LEVEL5 | D1261: Pump Repair Kit | E1261: Drywall Auto Tools | F1261: Repair Kits
A1262: 4-801 | B1262: 4-801 | C1262: LEVEL5 | D1262: Pump Rebuild Kit | E1262: Drywall Auto Tools | F1262: Repair Kits
A1263: 4-803 | B1263: 4-803 | C1263: LEVEL5 | D1263: Taper/Gooseneck Cleaning Kit | E1263: Drywall Auto Tools | F1263: Repair Kits
A1264: 4-805 | B1264: 4-805 | C1264: LEVEL5 | D1264: 7"Flat Box Seal | E1264: Drywall Auto Tools | F1264: Repair Kits
A1265: 4-807 | B1265: 4-807 | C1265: LEVEL5 | D1265: 12"Flat Box Seal | E1265: Drywall Auto Tools | F1265: Repair Kits
A1266: 4-808 | B1266: 4-808 | C1266: LEVEL5 | D1266: Flat Box Repair Kit | E1266: Drywall Auto Tools | F1266: Repair Kits
... A1293: 4-893 | B1293: 4-893 | C1293: LEVEL5 | D1293: 14" Box Gsket (Hinged Box) | E1293: Drywall Auto Tools | F1293: Repair Kits
A1294: 92180 | B1294: 92180 | C1294: Husky | D1294: Husky Corner Bead Tool w/ Rubber Mallet | E1294: Drywall Hand Tools | F1294: Bead Tools
A1295: 92731 | B1295: 92731 | C1295: Husky | D1295: Husky Stippiling Texture Brush 5" | E1295: Drywall Hand Tools | F1295: Brushes
A1296: 92732 | B1296: 92732 | C1296: Husky | D1296: Husky Single Texture Brush 9" x 13" | E1296: Drywall Hand Tools | F1296: Brushes
A1297: CMXTTLV95051 | B1297: 95051 | C1297: Craftsman | D1297: Craftsman Bucket w/ Lid | E1297: Drywall Hand Tools | F1297: Bucket
A1298: CMXTTLV95061 | B1298: 95061 | C1298: Craftsman | D1298: Craftsman 6" Bucket Scoop | E1298: Drywall Hand Tools | F1298: Bucket Scoops
A1299: 92755 | B1299: 92755 | C1299: Husky | D1299: Husky Drywall Bucket Scoop, Plastic | E1299: Drywall Hand Tools | F1299: Bucket Scoops
A1300: 5-210 | B1300: 5-210 | C1300: LEVEL5 | D1300: 6"SS Bucket Scoop | E1300: Drywall Hand Tools | F1300: Bucket Scoops
A1301: 92193 | B1301: 92193 | C1301: Husky | D1301: Husky 8.5" Drywall Circle Cutter | E1301: Drywall Hand Tools | F1301: Circle Cutters
A1302: 92780 | B1302: 92780 | C1302: Husky | D1302: Husky Hand Sander w/ Wood Handle | E1302: Drywall Hand Tools | F1302: Hand Sanders
A1303: 92781 | B1303: 92781 | C1303: Husky | D1303: Husky Hand Sander w/ Soft Grip Handle | E1303: Drywall Hand Tools | F1303: Hand Sanders
A1304: 822240 | B1304: 822240 | C1304: Anvil | D1304: Anvil 3PC Joint Knife QP | E1304: Drywall Hand Tools | F1304: Hand Tool Sets
A1305: CMXTTLV95050 | B1305: 95050 | C1305: Craftsman | D1305: Craftsman Drywall Hand Tool Kit w/Bucket | E1305: Drywall Hand Tools | F1305: Hand Tool Sets
A1306: CMXTTLV95052 | B1306: 95052 | C1306: Craftsman | D1306: Craftsman Drywall Hand Tool Kit | E1306: Drywall Hand Tools | F1306: Hand Tool Sets
A1307: 92771 | B1307: 92771 | C1307: DEWALT | D1307: DEWALT Rubber Soft Grip Stainless Steel Hammer End Putty Knife Set | E1307: Drywall Hand Tools | F1307: Hand Tool Sets
A1308: 822230 | B1308: 822230 | C1308: DEWALT | D1308: DEWALT 3PC SS J-Knife WeldHndl Blister Pk | E1308: Drywall Hand Tools | F1308: Hand Tool Sets
A1309: 3-208 | B1309: 3-208 | C1309: DEWALT | D1309: DEWALT 2PC Trim Puller | E1309: Drywall Hand Tools | F1309: Hand Tool Sets
A1310: 4-100 | B1310: 4-100 | C1310: DEWALT | D1310: HD Emergency Kit A | E1310: Drywall Hand Tools | F1310: Hand Tool Sets
A1311: 92771D | B1311: 92771D | C1311: DEWALT | D1311: Rubber Soft Grip Stainless Steel Hammer End Putty Knife Set - 36 in Display | E1311: Drywall Hand Tools | F1311: Hand Tool Sets
A1312: DXTT-2-600 | B1312: 2-600 | C1312: DEWALT | D1312: DEWALT Pro Tap-Fin Set w/M Ext Hndls | E1312: Drywall Auto Tools | F1312: Auto Tool Sets
A1313: DXTT-2-601 | B1313: 2-601 | C1313: DEWALT | D1313: DEWALT Pro Tap-Fin Set w/LG Ext Hndls | E1313: Drywall Auto Tools | F1313: Auto Tool Sets
A1314: DXTT-2-611 | B1314: 2-611 | C1314: DEWALT | D1314: DEWALT MEGA Taping Set w/LG Ext Hndls | E1314: Drywall Auto Tools | F1314: Auto Tool Sets
A1315: DXTT-2-614 | B1315: 2-614 | C1315: DEWALT | D1315: DEWALT MEGA Pro Taping w/LG Ext Hndls | E1315: Drywall Auto Tools | F1315: Auto Tool Sets
...

Sheet Order Summary
D1: Tier 1 Order Form Summary
A3: Customer: | E3: Order date:
A4: Ship To: | E4: PO#:
E5: Need by date:
E6: Carrier:
E11: Order Quantity | F11: Total Price
A12: Level5 | B12: Drywall Hand Tools | E12: =SUMIFS('Order Input - Level5'!L:L,'Order Input - Level5'!C:C,'Order Summary'!A12,'Order Input - Level5'!D:D,'Order Summary'!B12) -> 0 | F12: =SUMIFS('Order Input - Level5'!M:M,'Order Input - Level5'!C:C,'Order Summary'!A12,'Order Input - Level5'!D:D,'Order Summary'!B12) -> 0
A13: Level5 | B13: Drywall Semi Auto Tools | E13: =SUMIFS('Order Input - Level5'!L:L,'Order Input - Level5'!C:C,'Order Summary'!A13,'Order Input - Level5'!D:D,'Order Summary'!B13) -> 0 | F13: =SUMIFS('Order Input - Level5'!M:M,'Order Input - Level5'!C:C,'Order Summary'!A13,'Order Input - Level5'!D:D,'Order Summary'!B13) -> 0
A14: Level5 | B14: Drywall Auto Tools | E14: =SUMIFS('Order Input - Level5'!L:L,'Order Input - Level5'!C:C,'Order Summary'!A14,'Order Input - Level5'!D:D,'Order Summary'!B14) -> 0 | F14: =SUMIFS('Order Input - Level5'!M:M,'Order Input - Level5'!C:C,'Order Summary'!A14,'Order Input - Level5'!D:D,'Order Summary'!B14) -> 0
A15: DeWalt | B15: Drywall Hand Tools | E15: =SUMIFS('Order Input - DeWalt'!L:L,'Order Input - DeWalt'!C:C,'Order Summary'!A15,'Order Input - DeWalt'!D:D,'Order Summary'!B15) -> 0 | F15: =SUMIFS('Order Input - DeWalt'!M:M,'Order Input - DeWalt'!C:C,'Order Summary'!A15,'Order Input - DeWalt'!D:D,'Order Summary'!B15) -> 0
A16: DeWalt | B16: Concrete Hand Tools | E16: =SUMIFS('Order Input - DeWalt'!L:L,'Order Input - DeWalt'!C:C,'Order Summary'!A16,'Order Input - DeWalt'!D:D,'Order Summary'!B16) -> 0 | F16: =SUMIFS('Order Input - DeWalt'!M:M,'Order Input - DeWalt'!C:C,'Order Summary'!A16,'Order Input - DeWalt'!D:D,'Order Summary'!B16) -> 0
A17: DeWalt | B17: Drywall Semi Auto Tools | E17: =SUMIFS('Order Input - DeWalt'!L:L,'Order Input - DeWalt'!C:C,'Order Summary'!A17,'Order Input - DeWalt'!D:D,'Order Summary'!B17) -> 0 | F17: =SUMIFS('Order Input - DeWalt'!M:M,'Order Input - DeWalt'!C:C,'Order Summary'!A17,'Order Input - DeWalt'!D:D,'Order Summary'!B17) -> 0
A18: DeWalt | B18: Drywall Auto Tools | E18: =SUMIFS('Order Input - DeWalt'!L:L,'Order Input - DeWalt'!C:C,'Order Summary'!A18,'Order Input - DeWalt'!D:D,'Order Summary'!B18) -> 0 | F18: =SUMIFS('Order Input - DeWalt'!M:M,'Order Input - DeWalt'!C:C,'Order Summary'!A18,'Order Input - DeWalt'!D:D,'Order Summary'!B18) -> 0
B19: Individual Parts totals: | E19: ='Order Input-Individual Part '!K133 -> 0 | F19: ='Order Input-Individual Part '!L133 -> 0
B20: Part Kits totals: | E20: ='Order Input-Part Kits'!K74 -> 0 | F20: ='Order Input-Part Kits'!L74 -> 0
B21: Merch. And Marketing: | E21: ='Order Input-Merch. And Mktg'!K25 -> 0 | F21: ='Order Input-Merch. And Mktg'!L25 -> 0
B22: Order totals: | E22: =SUM(E12:E21) -> 0 | F22: =SUM(F12:F21) -> 0
A29: Ordering instructions:
A30: 1) Please enter order details (Customer name, Ship to address, PO#, etc.) on the top of this tab, the other tabs will populate
A31: 2) Enter the quantities you would like to order on the appropriate line item in the Order Input tabs and
A32: the Order Summary page will calculate your order totals.
A33: Please contact us at orders@level5tools.com if you have questions.

Sheet Order Input - Level5
H1: Order Form
A3: Customer: | C3: ='Order Summary'!B3 -> 0 | J3: Order date: | N3: ='Order Summary'!$F3 -> 0
A4: Ship To: | C4: ='Order Summary'!B4 -> 0 | J4: PO#: | N4: ='Order Summary'!$F4 -> 0
A5: ='Order Summary'!B5 -> 0 | J5: Need by date: | N5: ='Order Summary'!$F5 -> 0
A6: ='Order Summary'!B6 -> 0 | J6: Carrier: | N6: ='Order Summary'!$F6 -> 0
A7: Please note that the case quantities are noted for each Product. Ordering in multiples of inner case quantities helps us keep costs low to you and reduces damage during shipping.
A10: Part # | B10: Sku # | C10: Description | D10: Brand | E10: Product Group | F10: Product Type | G10: MSRP | H10: MAPP | I10: Your Price | J10: UOM | K10: Inner Case Qty | L10: Master Case Qty | M10: Order Quantity | N10: Total Price
A11: 449324 | B11: 4-001 | C11: 4" Mud Roller | D11: =_xlfn.XLOOKUP(B11,'Product Hierarchy'!A:A,'Product Hierarchy'!C:C) -> LEVEL5 | E11: =_xlfn.XLOOKUP(B11,'Product Hierarchy'!A:A,'Product Hierarchy'!E:E) -> Drywall Hand Tools | F11: =_xlfn.XLOOKUP(B11,'Product Hierarchy'!A:A,'Product Hierarchy'!F:F) -> Rollers | G11: 18.49 | H11: 16.64 | I11: 11.65 | J11: Each | K11: 12 | L11: 48 | N11: =M11*I11 -> 0
A12: 449325 | B12: 4-002 | C12: Corner Mud Roller | D12: =_xlfn.XLOOKUP(B12,'Product Hierarchy'!A:A,'Product Hierarchy'!C:C) -> LEVEL5 | E12: =_xlfn.XLOOKUP(B12,'Product Hierarchy'!A:A,'Product Hierarchy'!E:E) -> Drywall Hand Tools | F12: =_xlfn.XLOOKUP(B12,'Product Hierarchy'!A:A,'Product Hierarchy'!F:F) -> Rollers | G12: 21.99 | H12: 19.79 | I12: 13.85 | J12: Each | K12: 6 | L12: 24 | N12: =M12*I12 -> 0
A13: 449326 | B13: 4-003 | C13: 4" Mud Roller Frame | D13: =_xlfn.XLOOKUP(B13,'Product Hierarchy'!A:A,'Product Hierarchy'!C:C) -> LEVEL5 | E13: =_xlfn.XLOOKUP(B13,'Product Hierarchy'!A:A,'Product Hierarchy'!E:E) -> Drywall Hand Tools | F13: =_xlfn.XLOOKUP(B13,'Product Hierarchy'!A:A,'Product Hierarchy'!F:F) -> Rollers | G13: 12.99 | H13: 11.69 | I13: 8.18 | J13: Each | K13: 6 | L13: 24 | N13: =M13*I13 -> 0
A14: 449327 | B14: 4-004 | C14: Corner Mud Roller Frame | D14: =_xlfn.XLOOKUP(B14,'Product Hierarchy'!A:A,'Product Hierarchy'!C:C) -> LEVEL5 | E14: =_xlfn.XLOOKUP(B14,'Product Hierarchy'!A:A,'Product Hierarchy'!E:E) -> Drywall Hand Tools | F14: =_xlfn.XLOOKUP(B14,'Product Hierarchy'!A:A,'Product Hierarchy'!F:F) -> Rollers | G14: 12.99 | H14: 11.69 | I14: 8.18 | J14: Each | K14: 6 | L14: 24 | N14: =M14*I14 -> 0
A15: 449328 | B15: 4-005 | C15: 4" Mud Roller w/Frame | D15: =_xlfn.XLOOKUP(B15,'Product Hierarchy'!A:A,'Product Hierarchy'!C:C) -> LEVEL5 | E15: =_xlfn.XLOOKUP(B15,'Product Hierarchy'!A:A,'Product Hierarchy'!E:E) -> Drywall Hand Tools | F15: =_xlfn.XLOOKUP(B15,'Product Hierarchy'!A:A,'Product Hierarchy'!F:F) -> Rollers | G15: 31.48 | H15: 28.33 | I15: 19.83 | J15: Each | K15: 6 | L15: 24 | N15: =M15*I15 -> 0
A16: 449329 | B16: 4-006 | C16: Corner Mud Roller w/Frame | D16: =_xlfn.XLOOKUP(B16,'Product Hierarchy'!A:A,'Product Hierarchy'!C:C) -> LEVEL5 | E16: =_xlfn.XLOOKUP(B16,'Product Hierarchy'!A:A,'Product Hierarchy'!E:E) -> Drywall Hand Tools | F16: =_xlfn.XLOOKUP(B16,'Product Hierarchy'!A:A,'Product Hierarchy'!F:F) -> Rollers | G16: 34.98 | H16: 31.48 | I16: 22.04 | J16: Each | K16: 6 | L16: 24 | N16: =M16*I16 -> 0
A17: 449330 | B17: 4-007 | C17: 4" Mud Roller Cover 3pk | D17: =_xlfn.XLOOKUP(B17,'Product Hierarchy'!A:A,'Product Hierarchy'!C:C) -> LEVEL5 | E17: =_xlfn.XLOOKUP(B17,'Product Hierarchy'!A:A,'Product Hierarchy'!E:E) -> Drywall Hand Tools | F17: =_xlfn.XLOOKUP(B17,'Product Hierarchy'!A:A,'Product Hierarchy'!F:F) -> Rollers | G17: 55.47 | H17: 49.92 | I17: 34.94 | J17: Each | K17: 1 | L17: 1 | N17: =M17*I17 -> 0
A18: 449331 | B18: 4-008 | C18: Corner Mud Roller Cover 3pk | D18: =_xlfn.XLOOKUP(B18,'Product Hierarchy'!A:A,'Product Hierarchy'!C:C) -> LEVEL5 | E18: =_xlfn.XLOOKUP(B18,'Product Hierarchy'!A:A,'Product Hierarchy'!E:E) -> Drywall Hand Tools | F18: =_xlfn.XLOOKUP(B18,'Product Hierarchy'!A:A,'Product Hierarchy'!F:F) -> Rollers | G18: 65.97 | H18: 59.37 | I18: 41.56 | J18: Each | K18: 1 | L18: 1 | N18: =M18*I18 -> 0
A19: 449332 | B19: 4-009 | C19: 9"Mud Roller-3pk | D19: =_xlfn.XLOOKUP(B19,'Product Hierarchy'!A:A,'Product Hierarchy'!C:C) -> LEVEL5 | E19: =_xlfn.XLOOKUP(B19,'Product Hierarchy'!A:A,'Product Hierarchy'!E:E) -> Drywall Hand Tools | F19: =_xlfn.XLOOKUP(B19,'Product Hierarchy'!A:A,'Product Hierarchy'!F:F) -> Rollers | G19: 62.97 | H19: 56.67 | I19: 39.67 | J19: Each | K19: 1 | L19: 1 | N19: =M19*I19 -> 0
A20: 449333 | B20: 4-012 | C20: 12"Mud Roller-3pk | D20: =_xlfn.XLOOKUP(B20,'Product Hierarchy'!A:A,'Product Hierarchy'!C:C) -> LEVEL5 | E20: =_xlfn.XLOOKUP(B20,'Product Hierarchy'!A:A,'Product Hierarchy'!E:E) -> Drywall Hand Tools | F20: =_xlfn.XLOOKUP(B20,'Product Hierarchy'!A:A,'Product Hierarchy'!F:F) -> Rollers | G20: 68.97 | H20: 62.07 | I20: 43.45 | J20: Each | K20: 1 | L20: 1 | N20: =M20*I20 -> 0
A21: 449384 | B21: 4-600P | C21: Taping Finishing Set w/Fixed Hndls-P | D21: =_xlfn.XLOOKUP(B21,'Product Hierarchy'!A:A,'Product Hierarchy'!C:C) -> LEVEL5 | E21: =_xlfn.XLOOKUP(B21,'Product Hierarchy'!A:A,'Product Hierarchy'!E:E) -> Drywall Auto Tools | F21: =_xlfn.XLOOKUP(B21,'Product Hierarchy'!A:A,'Product Hierarchy'!F:F) -> Auto Tool Sets | G21: 4813.38 | H21: 3850.7 | I21: 2695.49 | J21: Each | K21: 1 | L21: 1 | N21: =M21*I21 -> 0
A22: 449386 | B22: 4-601P | C22: Taping Finishing Set w/Ext Hndls-P | D22: =_xlfn.XLOOKUP(B22,'Product Hierarchy'!A:A,'Product Hierarchy'!C:C) -> LEVEL5 | E22: =_xlfn.XLOOKUP(B22,'Product Hierarchy'!A:A,'Product Hierarchy'!E:E) -> Drywall Auto Tools | F22: =_xlfn.XLOOKUP(B22,'Product Hierarchy'!A:A,'Product Hierarchy'!F:F) -> Auto Tool Sets | G22: 5265.85 | H22: 4212.68 | I22: 2948.88 | J22: Each | K22: 1 | L22: 1 | N22: =M22*I22 -> 0
... A47: 449488 | B47: 4-735 | C47: 4"Corner Finisher | D47: =_xlfn.XLOOKUP(B47,'Product Hierarchy'!A:A,'Product Hierarchy'!C:C) -> LEVEL5 | E47: =_xlfn.XLOOKUP(B47,'Product Hierarchy'!A:A,'Product Hierarchy'!E:E) -> Drywall Auto Tools | F47: =_xlfn.XLOOKUP(B47,'Product Hierarchy'!A:A,'Product Hierarchy'!F:F) -> Corner Finishers | G47: 500.49 | H47: 425.42 | I47: 297.79 | J47: Each | K47: 1 | L47: 10 | N47: =M47*I47 -> 0
A48: 450989 | B48: 4-735CASE-B | C48: 4" Corner Finisher Case w/Foam Insert (No Tool) | D48: LEVEL5 | E48: Drywall Auto Tools | F48: Storage | G48: 53.49 | H48: 45.47 | I48: 31.83 | J48: Each | K48: 1 | L48: 10 | N48: =M48*I48 -> 0
A49: 449491 | B49: 4-740 | C49: 54"Fixed Flat Box Hndl | D49: =_xlfn.XLOOKUP(B49,'Product Hierarchy'!A:A,'Product Hierarchy'!C:C) -> LEVEL5 | E49: =_xlfn.XLOOKUP(B49,'Product Hierarchy'!A:A,'Product Hierarchy'!E:E) -> Drywall Auto Tools | F49: =_xlfn.XLOOKUP(B49,'Product Hierarchy'!A:A,'Product Hierarchy'!F:F) -> Handles | G49: 238.49 | H49: 202.72 | I49: 141.9 | J49: Each | K49: 6 | L49: 6 | N49: =M49*I49 -> 0
A50: 449493 | B50: 4-741 | C50: Comound Tube 42" | D50: =_xlfn.XLOOKUP(B50,'Product Hierarchy'!A:A,'Product Hierarchy'!C:C) -> LEVEL5 | E50: =_xlfn.XLOOKUP(B50,'Product Hierarchy'!A:A,'Product Hierarchy'!E:E) -> Drywall Semi Auto Tools | F50: =_xlfn.XLOOKUP(B50,'Product Hierarchy'!A:A,'Product Hierarchy'!F:F) -> Compound Dispensers | G50: 226.49 | H50: 203.84 | I50: 142.69 | J50: Each | K50: 1 | L50: 4 | N50: =M50*I50 -> 0
A51: 449495 | B51: 4-743 | C51: 3"Direct Corner Flusher w/Wheels | D51: =_xlfn.XLOOKUP(B51,'Product Hierarchy'!A:A,'Product Hierarchy'!C:C) -> LEVEL5 | E51: =_xlfn.XLOOKUP(B51,'Product Hierarchy'!A:A,'Product Hierarchy'!E:E) -> Drywall Semi Auto Tools | F51: =_xlfn.XLOOKUP(B51,'Product Hierarchy'!A:A,'Product Hierarchy'!F:F) -> Flushers | G51: 142.99 | H51: 128.69 | I51: 90.08 | J51: Each | K51: 1 | L51: 12 | N51: =M51*I51 -> 0
A52: 449496 | B52: 4-744 | C52: 3.5"Direct Corner Flusher w/Wheels | D52: =_xlfn.XLOOKUP(B52,'Product Hierarchy'!A:A,'Product Hierarchy'!C:C) -> LEVEL5 | E52: =_xlfn.XLOOKUP(B52,'Product Hierarchy'!A:A,'Product Hierarchy'!E:E) -> Drywall Semi Auto Tools | F52: =_xlfn.XLOOKUP(B52,'Product Hierarchy'!A:A,'Product Hierarchy'!F:F) -> Flushers | G52: 147.49 | H52: 132.74 | I52: 92.92 | J52: Each | K52: 1 | L52: 12 | N52: =M52*I52 -> 0
A53: 450718 | B53: 4-746 | C53: Outside Corner Bead Mud Applicator | D53: =_xlfn.XLOOKUP(B53,'Product Hierarchy'!A:A,'Product Hierarchy'!C:C) -> LEVEL5 | E53: =_xlfn.XLOOKUP(B53,'Product Hierarchy'!A:A,'Product Hierarchy'!E:E) -> Drywall Auto Tools | F53: =_xlfn.XLOOKUP(B53,'Product Hierarchy'!A:A,'Product Hierarchy'!F:F) -> Outside Applicator Head | G53: 86.99 | H53: 73.94 | I53: 51.76 | J53: Each | K53: 1 | L53: 12 | N53: =M53*I53 -> 0
A54: 449500 | B54: 4-749 | C54: CT Box Filler Attachment | D54: =_xlfn.XLOOKUP(B54,'Product Hierarchy'!A:A,'Product Hierarchy'!C:C) -> LEVEL5 | E54: =_xlfn.XLOOKUP(B54,'Product Hierarchy'!A:A,'Product Hierarchy'!E:E) -> Drywall Auto Tools | F54: =_xlfn.XLOOKUP(B54,'Product Hierarchy'!A:A,'Product Hierarchy'!F:F) -> Compound Dispensers | G54: 31.99 | H54: 27.19 | I54: 19.03 | J54: Each | K54: 1 | L54: 12 | N54: =M54*I54 -> 0
A55: 449501 | B55: 4-754 | C55: 2"Nail Spotter (2G) | D55: =_xlfn.XLOOKUP(B55,'Product Hierarchy'!A:A,'Product Hierarchy'!C:C) -> LEVEL5 | E55: =_xlfn.XLOOKUP(B55,'Product Hierarchy'!A:A,'Product Hierarchy'!E:E) -> Drywall Auto Tools | F55: =_xlfn.XLOOKUP(B55,'Product Hierarchy'!A:A,'Product Hierarchy'!F:F) -> Nail Spotters | G55: 318.99 | H55: 271.14 | I55: 189.8 | J55: Each | K55: 1 | L55: 10 | N55: =M55*I55 -> 0
A56: 450990 | B56: 4-754CASE-B | C56: 2" Nail Spotter Case w/Foam Insert (No Tool) | D56: =_xlfn.XLOOKUP(B56,'Product Hierarchy'!A:A,'Product Hierarchy'!C:C) -> LEVEL5 | E56: =_xlfn.XLOOKUP(B56,'Product Hierarchy'!A:A,'Product Hierarchy'!E:E) -> Drywall Auto Tools | F56: =_xlfn.XLOOKUP(B56,'Product Hierarchy'!A:A,'Product Hierarchy'!F:F) -> Storage | G56: 53.49 | H56: 45.47 | I56: 31.83 | J56: Each | K56: 1 | L56: 10 | N56: =M56*I56 -> 0
A57: 449505 | B57: 4-755 | C57: 3"Nail Spotter (2G) | D57: =_xlfn.XLOOKUP(B57,'Product Hierarchy'!A:A,'Product Hierarchy'!C:C) -> LEVEL5 | E57: =_xlfn.XLOOKUP(B57,'Product Hierarchy'!A:A,'Product Hierarchy'!E:E) -> Drywall Auto Tools | F57: =_xlfn.XLOOKUP(B57,'Product Hierarchy'!A:A,'Product Hierarchy'!F:F) -> Nail Spotters | G57: 340.99 | H57: 289.84 | I57: 202.89 | J57: Each | K57: 1 | L57: 10 | N57: =M57*I57 -> 0
A58: 450991 | B58: 4-755CASE-B | C58: 3" Nail Spotter Case w/Foam Insert (No Tool) | D58: =_xlfn.XLOOKUP(B58,'Product Hierarchy'!A:A,'Product Hierarchy'!C:C) -> LEVEL5 | E58: =_xlfn.XLOOKUP(B58,'Product Hierarchy'!A:A,'Product Hierarchy'!E:E) -> Drywall Auto Tools | F58: =_xlfn.XLOOKUP(B58,'Product Hierarchy'!A:A,'Product Hierarchy'!F:F) -> Storage | G58: 53.49 | H58: 45.47 | I58: 31.83 | J58: Each | K58: 1 | L58: 10 | N58: =M58*I58 -> 0
A59: 449515 | B59: 4-759 | C59: 48"- 78"Flat Box Ext Hndl | D59: =_xlfn.XLOOKUP(B59,'Product Hierarchy'!A:A,'Product Hierarchy'!C:C) -> LEVEL5 | E59: =_xlfn.XLOOKUP(B59,'Product Hierarchy'!A:A,'Product Hierarchy'!E:E) -> Drywall Auto Tools | F59: =_xlfn.XLOOKUP(B59,'Product Hierarchy'!A:A,'Product Hierarchy'!F:F) -> Handles | G59: 368.49 | H59: 313.22 | I59: 219.25 | J59: Each | K59: 6 | L59: 6 | N59: =M59*I59 -> 0
A60: 449517 | B60: 4-760 | C60: Automatic Drywall Taper (2G) | D60: =_xlfn.XLOOKUP(B60,'Product Hierarchy'!A:A,'Product Hierarchy'!C:C) -> LEVEL5 | E60: =_xlfn.XLOOKUP(B60,'Product Hierarchy'!A:A,'Product Hierarchy'!E:E) -> Drywall Auto Tools | F60: =_xlfn.XLOOKUP(B60,'Product Hierarchy'!A:A,'Product Hierarchy'!F:F) -> Auto Tapers | G60: 1699.99 | H60: 1444.99 | I60: 1011.49 | J60: Each | K60: 1 | L60: 4 | N60: =M60*I60 -> 0
... A202: 449767 | B202: 5-311 | C202: Banjo | D202: =_xlfn.XLOOKUP(B202,'Product Hierarchy'!A:A,'Product Hierarchy'!C:C) -> LEVEL5 | E202: =_xlfn.XLOOKUP(B202,'Product Hierarchy'!A:A,'Product Hierarchy'!E:E) -> Drywall Semi Auto Tools | F202: =_xlfn.XLOOKUP(B202,'Product Hierarchy'!A:A,'Product Hierarchy'!F:F) -> Banjos | G202: 166.99 | H202: 150.29 | I202: 105.2 | J202: Each | K202: 1 | L202: 6 | N202: =M202*I202 -> 0
A203: 451003 | B203: 5-311CASE-H | C203: Banjo Case W/Foam Insert (NO TOOL) | D203: LEVEL5 | E203: Drywall Semi Auto Tools | F203: Storage | G203: 59.99 | H203: 53.99 | I203: 37.79 | J203: Each | K203: 1 | L203: 8 | N203: =M203*I203 -> 0
A204: 449769 | B204: 5-312 | C204: 6.5"x11.5"SS Corner Trowel-Sft Grp | D204: =_xlfn.XLOOKUP(B204,'Product Hierarchy'!A:A,'Product Hierarchy'!C:C) -> LEVEL5 | E204: =_xlfn.XLOOKUP(B204,'Product Hierarchy'!A:A,'Product Hierarchy'!E:E) -> Drywall Hand Tools | F204: =_xlfn.XLOOKUP(B204,'Product Hierarchy'!A:A,'Product Hierarchy'!F:F) -> Inside Corner Trowels | G204: 16.49 | H204: 14.84 | I204: 10.39 | J204: Each | K204: 6 | L204: 36 | N204: =M204*I204 -> 0
A205: 449770 | B205: 5-320 | C205: 4"x3.5"SS Corner Trowel-Sft Grp | D205: =_xlfn.XLOOKUP(B205,'Product Hierarchy'!A:A,'Product Hierarchy'!C:C) -> LEVEL5 | E205: =_xlfn.XLOOKUP(B205,'Product Hierarchy'!A:A,'Product Hierarchy'!E:E) -> Drywall Hand Tools | F205: =_xlfn.XLOOKUP(B205,'Product Hierarchy'!A:A,'Product Hierarchy'!F:F) -> Outside Corner Trowels | G205: 14.49 | H205: 13.04 | I205: 9.13 | J205: Each | K205: 6 | L205: 36 | N205: =M205*I205 -> 0
A206: 449771 | B206: 5-325 | C206: Hawk 13" x 13" | D206: =_xlfn.XLOOKUP(B206,'Product Hierarchy'!A:A,'Product Hierarchy'!C:C) -> LEVEL5 | E206: =_xlfn.XLOOKUP(B206,'Product Hierarchy'!A:A,'Product Hierarchy'!E:E) -> Drywall Hand Tools | F206: =_xlfn.XLOOKUP(B206,'Product Hierarchy'!A:A,'Product Hierarchy'!F:F) -> Hawks | G206: 49.99 | H206: 44.99 | I206: 31.49 | J206: Each | K206: 4 | L206: 4 | N206: =M206*I206 -> 0
A207: 449773 | B207: 5-326 | C207: Hawk 16" x 16" | D207: =_xlfn.XLOOKUP(B207,'Product Hierarchy'!A:A,'Product Hierarchy'!C:C) -> LEVEL5 | E207: =_xlfn.XLOOKUP(B207,'Product Hierarchy'!A:A,'Product Hierarchy'!E:E) -> Drywall Hand Tools | F207: =_xlfn.XLOOKUP(B207,'Product Hierarchy'!A:A,'Product Hierarchy'!F:F) -> Hawks | G207: 60.49 | H207: 54.44 | I207: 38.11 | J207: Each | K207: 1 | L207: 4 | N207: =M207*I207 -> 0
A208: 449775 | B208: 5-332 | C208: 12"SS Mud Pan | D208: =_xlfn.XLOOKUP(B208,'Product Hierarchy'!A:A,'Product Hierarchy'!C:C) -> LEVEL5 | E208: =_xlfn.XLOOKUP(B208,'Product Hierarchy'!A:A,'Product Hierarchy'!E:E) -> Drywall Hand Tools | F208: =_xlfn.XLOOKUP(B208,'Product Hierarchy'!A:A,'Product Hierarchy'!F:F) -> Mud Pans | G208: 23.99 | H208: 21.59 | I208: 15.11 | J208: Each | K208: 6 | L208: 12 | N208: =M208*I208 -> 0
A209: 449776 | B209: 5-334 | C209: 14"SS Mud Pan | D209: LEVEL5 | E209: Drywall Hand Tools | F209: Mud Pans | G209: 24.99 | H209: 22.49 | I209: 15.74 | J209: Each | K209: 6 | L209: 12 | N209: =M209*I209 -> 0
A210: 449777 | B210: 5-336 | C210: 16"SS Mud Pan | D210: =_xlfn.XLOOKUP(B210,'Product Hierarchy'!A:A,'Product Hierarchy'!C:C) -> LEVEL5 | E210: =_xlfn.XLOOKUP(B210,'Product Hierarchy'!A:A,'Product Hierarchy'!E:E) -> Drywall Hand Tools | F210: =_xlfn.XLOOKUP(B210,'Product Hierarchy'!A:A,'Product Hierarchy'!F:F) -> Mud Pans | G210: 25.99 | H210: 23.39 | I210: 16.37 | J210: Each | K210: 6 | L210: 12 | N210: =M210*I210 -> 0
A211: 449779 | B211: 5-342 | C211: 9" Radial Sander | D211: =_xlfn.XLOOKUP(B211,'Product Hierarchy'!A:A,'Product Hierarchy'!C:C) -> LEVEL5 | E211: =_xlfn.XLOOKUP(B211,'Product Hierarchy'!A:A,'Product Hierarchy'!E:E) -> Drywall Hand Tools | F211: =_xlfn.XLOOKUP(B211,'Product Hierarchy'!A:A,'Product Hierarchy'!F:F) -> Radial Sanders | G211: 43.49 | H211: 39.14 | I211: 27.4 | J211: Each | K211: 1 | L211: 12 | N211: =M211*I211 -> 0
A212: 449780 | B212: 5-343 | C212: 48" Radial Sander Pole | D212: =_xlfn.XLOOKUP(B212,'Product Hierarchy'!A:A,'Product Hierarchy'!C:C) -> LEVEL5 | E212: =_xlfn.XLOOKUP(B212,'Product Hierarchy'!A:A,'Product Hierarchy'!E:E) -> Drywall Hand Tools | F212: =_xlfn.XLOOKUP(B212,'Product Hierarchy'!A:A,'Product Hierarchy'!F:F) -> Radial Sanders | G212: 26.99 | H212: 24.29 | I212: 17 | J212: Each | K212: 1 | L212: 24 | N212: =M212*I212 -> 0
A213: 449782 | B213: 5-345 | C213: 80 Grit 9" Radial Sander Disc-10pk | D213: =_xlfn.XLOOKUP(B213,'Product Hierarchy'!A:A,'Product Hierarchy'!C:C) -> LEVEL5 | E213: =_xlfn.XLOOKUP(B213,'Product Hierarchy'!A:A,'Product Hierarchy'!E:E) -> Drywall Hand Tools | F213: =_xlfn.XLOOKUP(B213,'Product Hierarchy'!A:A,'Product Hierarchy'!F:F) -> Sanding Discs | G213: 19.49 | H213: 17.54 | I213: 12.28 | J213: Each | K213: 4 | L213: 24 | N213: =M213*I213 -> 0
A214: 449783 | B214: 5-346 | C214: 120 Grit 9" Radial Sander Disc-10pk | D214: =_xlfn.XLOOKUP(B214,'Product Hierarchy'!A:A,'Product Hierarchy'!C:C) -> LEVEL5 | E214: =_xlfn.XLOOKUP(B214,'Product Hierarchy'!A:A,'Product Hierarchy'!E:E) -> Drywall Hand Tools | F214: =_xlfn.XLOOKUP(B214,'Product Hierarchy'!A:A,'Product Hierarchy'!F:F) -> Sanding Discs | G214: 19.49 | H214: 17.54 | I214: 12.28 | J214: Each | K214: 4 | L214: 24 | N214: =M214*I214 -> 0
A215: 449784 | B215: 5-347 | C215: 150 Grit 9" Radial Sander Disc-10pk | D215: =_xlfn.XLOOKUP(B215,'Product Hierarchy'!A:A,'Product Hierarchy'!C:C) -> LEVEL5 | E215: =_xlfn.XLOOKUP(B215,'Product Hierarchy'!A:A,'Product Hierarchy'!E:E) -> Drywall Hand Tools | F215: =_xlfn.XLOOKUP(B215,'Product Hierarchy'!A:A,'Product Hierarchy'!F:F) -> Sanding Discs | G215: 19.49 | H215: 17.54 | I215: 12.28 | J215: Each | K215: 4 | L215: 24 | N215: =M215*I215 -> 0
A216: 449785 | B216: 5-348 | C216: 180 Grit 9" Radial Sander Disc-10pk | D216: =_xlfn.XLOOKUP(B216,'Product Hierarchy'!A:A,'Product Hierarchy'!C:C) -> LEVEL5 | E216: =_xlfn.XLOOKUP(B216,'Product Hierarchy'!A:A,'Product Hierarchy'!E:E) -> Drywall Hand Tools | F216: =_xlfn.XLOOKUP(B216,'Product Hierarchy'!A:A,'Product Hierarchy'!F:F) -> Sanding Discs | G216: 19.49 | H216: 17.54 | I216: 12.28 | J216: Each | K216: 4 | L216: 24 | N216: =M216*I216 -> 0
A217: 449786 | B217: 5-349 | C217: 200 Grit 9" Radial Sander Disc-10pk | D217: =_xlfn.XLOOKUP(B217,'Product Hierarchy'!A:A,'Product Hierarchy'!C:C) -> LEVEL5 | E217: =_xlfn.XLOOKUP(B217,'Product Hierarchy'!A:A,'Product Hierarchy'!E:E) -> Drywall Hand Tools | F217: =_xlfn.XLOOKUP(B217,'Product Hierarchy'!A:A,'Product Hierarchy'!F:F) -> Sanding Discs | G217: 19.49 | H217: 17.54 | I217: 12.28 | J217: Each | K217: 4 | L217: 24 | N217: =M217*I217 -> 0
A218: 449787 | B218: 5-350 | C218: 220 Grit 9" Radial Sander Disc-10pk | D218: =_xlfn.XLOOKUP(B218,'Product Hierarchy'!A:A,'Product Hierarchy'!C:C) -> LEVEL5 | E218: =_xlfn.XLOOKUP(B218,'Product Hierarchy'!A:A,'Product Hierarchy'!E:E) -> Drywall Hand Tools | F218: =_xlfn.XLOOKUP(B218,'Product Hierarchy'!A:A,'Product Hierarchy'!F:F) -> Sanding Discs | G218: 19.49 | H218: 17.54 | I218: 12.28 | J218: Each | K218: 4 | L218: 24 | N218: =M218*I218 -> 0
A219: 449790 | B219: 5-360 | C219: 20" Laptop Style Tool Bag | D219: =_xlfn.XLOOKUP(B219,'Product Hierarchy'!A:A,'Product Hierarchy'!C:C) -> LEVEL5 | E219: =_xlfn.XLOOKUP(B219,'Product Hierarchy'!A:A,'Product Hierarchy'!E:E) -> Drywall Hand Tools | F219: =_xlfn.XLOOKUP(B219,'Product Hierarchy'!A:A,'Product Hierarchy'!F:F) -> Storage | G219: 124.99 | H219: 112.49 | I219: 78.74 | J219: Each | K219: 1 | L219: 6 | N219: =M219*I219 -> 0
A220: 449791 | B220: 5-362 | C220: 24" Duffle Style Tool Bag | D220: =_xlfn.XLOOKUP(B220,'Product Hierarchy'!A:A,'Product Hierarchy'!C:C) -> LEVEL5 | E220: =_xlfn.XLOOKUP(B220,'Product Hierarchy'!A:A,'Product Hierarchy'!E:E) -> Drywall Hand Tools | F220: =_xlfn.XLOOKUP(B220,'Product Hierarchy'!A:A,'Product Hierarchy'!F:F) -> Storage | G220: 134.99 | H220: 121.49 | I220: 85.04 | J220: Each | K220: 1 | L220: 2 | N220: =M220*I220 -> 0
A221: 449792 | B221: 5-380 | C221: 8"SS OffSet T-Knife-Stiff w/Adpt | D221: =_xlfn.XLOOKUP(B221,'Product Hierarchy'!A:A,'Product Hierarchy'!C:C) -> LEVEL5 | E221: =_xlfn.XLOOKUP(B221,'Product Hierarchy'!A:A,'Product Hierarchy'!E:E) -> Drywall Hand Tools | F221: =_xlfn.XLOOKUP(B221,'Product Hierarchy'!A:A,'Product Hierarchy'!F:F) -> Taping Knives | G221: 30.49 | H221: 27.44 | I221: 19.21 | J221: Each | K221: 4 | L221: 48 | N221: =M221*I221 -> 0
... A272: 449992 | B272: 8-334 | C272: 14"SS Mud Pan | D272: =_xlfn.XLOOKUP(B272,'Product Hierarchy'!A:A,'Product Hierarchy'!C:C) -> LEVEL5 | E272: =_xlfn.XLOOKUP(B272,'Product Hierarchy'!A:A,'Product Hierarchy'!E:E) -> Drywall Hand Tools | F272: =_xlfn.XLOOKUP(B272,'Product Hierarchy'!A:A,'Product Hierarchy'!F:F) -> Mud Pans | G272: 24.99 | H272: 22.49 | I272: 15.74 | J272: Each | K272: 6 | L272: 12 | N272: =M272*I272 -> 0
J273: Level5 Totals: | M273: =SUM(M11:M272) -> 0 | N273: =SUM(N11:N272) -> 0

Sheet Order Input - DeWalt
H1: Order Form
A3: Customer: | C3: ='Order Summary'!B3 -> 0 | J3: Order date: | N3: ='Order Summary'!$F3 -> 0
A4: Ship To: | C4: ='Order Summary'!B4 -> 0 | J4: PO#: | N4: ='Order Summary'!$F4 -> 0
A5: ='Order Summary'!B5 -> 0 | J5: Need by date: | N5: ='Order Summary'!$F5 -> 0
A6: ='Order Summary'!B6 -> 0 | J6: Carrier: | N6: ='Order Summary'!$F6 -> 0
A7: Please note that the case quantities are noted for each Product. Ordering in multiples of inner case quantities helps us keep costs low to you and reduces damage during shipping.
A10: Part # | B10: Sku # | C10: Description | D10: Brand | E10: Product Group | F10: Product Type | G10: MSRP | H10: MAPP | I10: Your Price | J10: UOM | K10: Inner Case Qty | L10: Master Case Qty | M10: Order Quantity | N10: Total Price
A11: 450016 | B11: DXTT-2-122 | C11: DEWALT 6"BS Taping Knife-Sft Grp Hndl | D11: =_xlfn.XLOOKUP(B11,'Product Hierarchy'!A:A,'Product Hierarchy'!C:C) -> DEWALT | E11: =_xlfn.XLOOKUP(B11,'Product Hierarchy'!A:A,'Product Hierarchy'!E:E) -> Drywall Hand Tools | F11: =_xlfn.XLOOKUP(B11,'Product Hierarchy'!A:A,'Product Hierarchy'!F:F) -> Taping Knives | G11: 17.49 | H11: 15.74 | I11: 11.02 | J11: Each | K11: 4 | L11: 24 | N11: =M11*I11 -> 0
A12: 450017 | B12: DXTT-2-124 | C12: DEWALT 8"BS Taping Knife-Sft Grp Hndl | D12: =_xlfn.XLOOKUP(B12,'Product Hierarchy'!A:A,'Product Hierarchy'!C:C) -> DEWALT | E12: =_xlfn.XLOOKUP(B12,'Product Hierarchy'!A:A,'Product Hierarchy'!E:E) -> Drywall Hand Tools | F12: =_xlfn.XLOOKUP(B12,'Product Hierarchy'!A:A,'Product Hierarchy'!F:F) -> Taping Knives | G12: 18.49 | H12: 16.64 | I12: 11.65 | J12: Each | K12: 4 | L12: 24 | N12: =M12*I12 -> 0
A13: 450018 | B13: DXTT-2-126 | C13: DEWALT 10"BS Taping Knife-Sft Grp Hndl | D13: =_xlfn.XLOOKUP(B13,'Product Hierarchy'!A:A,'Product Hierarchy'!C:C) -> DEWALT | E13: =_xlfn.XLOOKUP(B13,'Product Hierarchy'!A:A,'Product Hierarchy'!E:E) -> Drywall Hand Tools | F13: =_xlfn.XLOOKUP(B13,'Product Hierarchy'!A:A,'Product Hierarchy'!F:F) -> Taping Knives | G13: 19.49 | H13: 17.54 | I13: 12.28 | J13: Each | K13: 4 | L13: 24 | N13: =M13*I13 -> 0
A14: 450019 | B14: DXTT-2-127 | C14: DEWALT 12"BS Taping Knife-Sft Grp Hndl | D14: =_xlfn.XLOOKUP(B14,'Product Hierarchy'!A:A,'Product Hierarchy'!C:C) -> DEWALT | E14: =_xlfn.XLOOKUP(B14,'Product Hierarchy'!A:A,'Product Hierarchy'!E:E) -> Drywall Hand Tools | F14: =_xlfn.XLOOKUP(B14,'Product Hierarchy'!A:A,'Product Hierarchy'!F:F) -> Taping Knives | G14: 20.99 | H14: 18.89 | I14: 13.22 | J14: Each | K14: 4 | L14: 24 | N14: =M14*I14 -> 0
A15: 450020 | B15: DXTT-2-128 | C15: DEWALT 14"BS Taping Knife-Sft Grp Hndl | D15: =_xlfn.XLOOKUP(B15,'Product Hierarchy'!A:A,'Product Hierarchy'!C:C) -> DEWALT | E15: =_xlfn.XLOOKUP(B15,'Product Hierarchy'!A:A,'Product Hierarchy'!E:E) -> Drywall Hand Tools | F15: =_xlfn.XLOOKUP(B15,'Product Hierarchy'!A:A,'Product Hierarchy'!F:F) -> Taping Knives | G15: 21.99 | H15: 19.79 | I15: 13.85 | J15: Each | K15: 4 | L15: 24 | N15: =M15*I15 -> 0
A16: 450021 | B16: DXTT-2-134 | C16: DEWALT 8"SS Taping Knife-Sft Grp Hndl | D16: =_xlfn.XLOOKUP(B16,'Product Hierarchy'!A:A,'Product Hierarchy'!C:C) -> DEWALT | E16: =_xlfn.XLOOKUP(B16,'Product Hierarchy'!A:A,'Product Hierarchy'!E:E) -> Drywall Hand Tools | F16: =_xlfn.XLOOKUP(B16,'Product Hierarchy'!A:A,'Product Hierarchy'!F:F) -> Taping Knives | G16: 18.49 | H16: 16.64 | I16: 11.65 | J16: Each | K16: 4 | L16: 24 | N16: =M16*I16 -> 0
A17: 450022 | B17: DXTT-2-136 | C17: DEWALT 10"SS Taping Knife-Sft Grp Hndl | D17: =_xlfn.XLOOKUP(B17,'Product Hierarchy'!A:A,'Product Hierarchy'!C:C) -> DEWALT | E17: =_xlfn.XLOOKUP(B17,'Product Hierarchy'!A:A,'Product Hierarchy'!E:E) -> Drywall Hand Tools | F17: =_xlfn.XLOOKUP(B17,'Product Hierarchy'!A:A,'Product Hierarchy'!F:F) -> Taping Knives | G17: 19.49 | H17: 17.54 | I17: 12.28 | J17: Each | K17: 4 | L17: 24 | N17: =M17*I17 -> 0
A18: 450023 | B18: DXTT-2-137 | C18: DEWALT 12"SS Taping Knife-Sft Grp Hndl | D18: =_xlfn.XLOOKUP(B18,'Product Hierarchy'!A:A,'Product Hierarchy'!C:C) -> DEWALT | E18: =_xlfn.XLOOKUP(B18,'Product Hierarchy'!A:A,'Product Hierarchy'!E:E) -> Drywall Hand Tools | F18: =_xlfn.XLOOKUP(B18,'Product Hierarchy'!A:A,'Product Hierarchy'!F:F) -> Taping Knives | G18: 20.99 | H18: 18.89 | I18: 13.22 | J18: Each | K18: 4 | L18: 24 | N18: =M18*I18 -> 0
A19: 450024 | B19: DXTT-2-138 | C19: DEWALT 14"SS Taping Knife-Sft Grp Hndl | D19: =_xlfn.XLOOKUP(B19,'Product Hierarchy'!A:A,'Product Hierarchy'!C:C) -> DEWALT | E19: =_xlfn.XLOOKUP(B19,'Product Hierarchy'!A:A,'Product Hierarchy'!E:E) -> Drywall Hand Tools | F19: =_xlfn.XLOOKUP(B19,'Product Hierarchy'!A:A,'Product Hierarchy'!F:F) -> Taping Knives | G19: 21.99 | H19: 19.79 | I19: 13.85 | J19: Each | K19: 4 | L19: 24 | N19: =M19*I19 -> 0
A20: 450025 | B20: DXTT-2-139 | C20: DEWALT 3"SS Joint Knife-Sft Grp Hndl | D20: =_xlfn.XLOOKUP(B20,'Product Hierarchy'!A:A,'Product Hierarchy'!C:C) -> DEWALT | E20: =_xlfn.XLOOKUP(B20,'Product Hierarchy'!A:A,'Product Hierarchy'!E:E) -> Drywall Hand Tools | F20: =_xlfn.XLOOKUP(B20,'Product Hierarchy'!A:A,'Product Hierarchy'!F:F) -> Joint Knives | G20: 15.49 | H20: 13.94 | I20: 9.76 | J20: Each | K20: 8 | L20: 48 | N20: =M20*I20 -> 0
A21: 450026 | B21: DXTT-2-140 | C21: DEWALT 4"SS Joint Knife-Sft Grp Hndl | D21: =_xlfn.XLOOKUP(B21,'Product Hierarchy'!A:A,'Product Hierarchy'!C:C) -> DEWALT | E21: =_xlfn.XLOOKUP(B21,'Product Hierarchy'!A:A,'Product Hierarchy'!E:E) -> Drywall Hand Tools | F21: =_xlfn.XLOOKUP(B21,'Product Hierarchy'!A:A,'Product Hierarchy'!F:F) -> Joint Knives | G21: 16.49 | H21: 14.84 | I21: 10.39 | J21: Each | K21: 8 | L21: 48 | N21: =M21*I21 -> 0
A22: 450029 | B22: DXTT-2-144 | C22: DEWALT 8"SS Joint Knife-Sft Grp Hndl | D22: =_xlfn.XLOOKUP(B22,'Product Hierarchy'!A:A,'Product Hierarchy'!C:C) -> DEWALT | E22: =_xlfn.XLOOKUP(B22,'Product Hierarchy'!A:A,'Product Hierarchy'!E:E) -> Drywall Hand Tools | F22: =_xlfn.XLOOKUP(B22,'Product Hierarchy'!A:A,'Product Hierarchy'!F:F) -> Joint Knives | G22: 20.99 | H22: 18.89 | I22: 13.22 | J22: Each | K22: 8 | L22: 48 | N22: =M22*I22 -> 0
... A44: 450057 | B44: DXTT-2-202 | C44: DEWALT SS Pointed Knife -Sft Grp Hndl | D44: =_xlfn.XLOOKUP(B44,'Product Hierarchy'!A:A,'Product Hierarchy'!C:C) -> DEWALT | E44: =_xlfn.XLOOKUP(B44,'Product Hierarchy'!A:A,'Product Hierarchy'!E:E) -> Drywall Hand Tools | F44: =_xlfn.XLOOKUP(B44,'Product Hierarchy'!A:A,'Product Hierarchy'!F:F) -> Specialty Knives | G44: 15.99 | H44: 14.39 | I44: 10.07 | J44: Each | K44: 8 | L44: 48 | N44: =M44*I44 -> 0
A45: 450058 | B45: DXTT-2-203 | C45: DEWALT 4" Trim Puller - 4-In-1 Multi Tool | D45: DEWALT | E45: Drywall Hand Tools | F45: Trim Puller | G45: 21.99 | H45: 17.99 | I45: 12.59 | J45: Each | K45: 4 | L45: 40 | N45: =M45*I45 -> 0
A46: 450059 | B46: DXTT-2-291 | C46: DEWALT Mixer 5" Head 32" Shaft | D46: =_xlfn.XLOOKUP(B46,'Product Hierarchy'!A:A,'Product Hierarchy'!C:C) -> DEWALT | E46: =_xlfn.XLOOKUP(B46,'Product Hierarchy'!A:A,'Product Hierarchy'!E:E) -> Drywall Hand Tools | F46: =_xlfn.XLOOKUP(B46,'Product Hierarchy'!A:A,'Product Hierarchy'!F:F) -> Mixers | G46: 36.49 | H46: 32.84 | I46: 22.99 | J46: Each | K46: 4 | L46: 4 | N46: =M46*I46 -> 0
A47: 450060 | B47: DXTT-2-292 | C47: DEWALT Mixer 7" Head 32" Shaft | D47: =_xlfn.XLOOKUP(B47,'Product Hierarchy'!A:A,'Product Hierarchy'!C:C) -> DEWALT | E47: =_xlfn.XLOOKUP(B47,'Product Hierarchy'!A:A,'Product Hierarchy'!E:E) -> Drywall Hand Tools | F47: =_xlfn.XLOOKUP(B47,'Product Hierarchy'!A:A,'Product Hierarchy'!F:F) -> Mixers | G47: 45.49 | H47: 40.94 | I47: 28.66 | J47: Each | K47: 2 | L47: 2 | N47: =M47*I47 -> 0
A48: 450061 | B48: DXTT-2-293 | C48: DEWALT Mixer 2" Head 13" Shaft | D48: =_xlfn.XLOOKUP(B48,'Product Hierarchy'!A:A,'Product Hierarchy'!C:C) -> DEWALT | E48: =_xlfn.XLOOKUP(B48,'Product Hierarchy'!A:A,'Product Hierarchy'!E:E) -> Drywall Hand Tools | F48: =_xlfn.XLOOKUP(B48,'Product Hierarchy'!A:A,'Product Hierarchy'!F:F) -> Mixers | G48: 15.99 | H48: 14.39 | I48: 10.07 | J48: Each | K48: 16 | L48: 16 | N48: =M48*I48 -> 0
A49: 450062 | B49: DXTT-2-294 | C49: DEWALT Mixer 4" Head 28" Shaft | D49: =_xlfn.XLOOKUP(B49,'Product Hierarchy'!A:A,'Product Hierarchy'!C:C) -> DEWALT | E49: =_xlfn.XLOOKUP(B49,'Product Hierarchy'!A:A,'Product Hierarchy'!E:E) -> Drywall Hand Tools | F49: =_xlfn.XLOOKUP(B49,'Product Hierarchy'!A:A,'Product Hierarchy'!F:F) -> Mixers | G49: 30.49 | H49: 27.44 | I49: 19.21 | J49: Each | K49: 8 | L49: 8 | N49: =M49*I49 -> 0
A50: 450063 | B50: DXTT-2-295 | C50: DEWALT Mixer Adaptor-w/HexKey | D50: =_xlfn.XLOOKUP(B50,'Product Hierarchy'!A:A,'Product Hierarchy'!C:C) -> DEWALT | E50: =_xlfn.XLOOKUP(B50,'Product Hierarchy'!A:A,'Product Hierarchy'!E:E) -> Drywall Hand Tools | F50: =_xlfn.XLOOKUP(B50,'Product Hierarchy'!A:A,'Product Hierarchy'!F:F) -> Mixers | G50: 13.49 | H50: 12.14 | I50: 8.5 | J50: Each | K50: 1 | L50: 40 | N50: =M50*I50 -> 0
A51: 450064 | B51: DXTT-2-302 | C51: DEWALT 48" HD Drywall T-Square | D51: =_xlfn.XLOOKUP(B51,'Product Hierarchy'!A:A,'Product Hierarchy'!C:C) -> DEWALT | E51: =_xlfn.XLOOKUP(B51,'Product Hierarchy'!A:A,'Product Hierarchy'!E:E) -> Drywall Hand Tools | F51: =_xlfn.XLOOKUP(B51,'Product Hierarchy'!A:A,'Product Hierarchy'!F:F) -> T-Square | G51: 32.49 | H51: 29.24 | I51: 20.47 | J51: Each | K51: 1 | L51: 4 | N51: =M51*I51 -> 0
A52: 450065 | B52: DXTT-2-305 | C52: DEWALT Pro Texture Sprayer with Hopper | D52: =_xlfn.XLOOKUP(B52,'Product Hierarchy'!A:A,'Product Hierarchy'!C:C) -> DEWALT | E52: =_xlfn.XLOOKUP(B52,'Product Hierarchy'!A:A,'Product Hierarchy'!E:E) -> Drywall Semi Auto Tools | F52: =_xlfn.XLOOKUP(B52,'Product Hierarchy'!A:A,'Product Hierarchy'!F:F) -> Hopper Gun | G52: 151.49 | H52: 136.34 | I52: 95.44 | J52: Each | K52: 1 | L52: 2 | N52: =M52*I52 -> 0
A53: 450066 | B53: DXTT-2-306 | C53: DEWALT Texture Hopper Gun Nozzles | D53: =_xlfn.XLOOKUP(B53,'Product Hierarchy'!A:A,'Product Hierarchy'!C:C) -> DEWALT | E53: =_xlfn.XLOOKUP(B53,'Product Hierarchy'!A:A,'Product Hierarchy'!E:E) -> Drywall Semi Auto Tools | F53: =_xlfn.XLOOKUP(B53,'Product Hierarchy'!A:A,'Product Hierarchy'!F:F) -> Hopper Gun | G53: 16.49 | H53: 14.84 | I53: 10.39 | J53: Each | K53: 6 | L53: 24 | N53: =M53*I53 -> 0
A54: 450068 | B54: DXTT-2-325 | C54: DEWALT Hawk 13" x 13" | D54: =_xlfn.XLOOKUP(B54,'Product Hierarchy'!A:A,'Product Hierarchy'!C:C) -> DEWALT | E54: =_xlfn.XLOOKUP(B54,'Product Hierarchy'!A:A,'Product Hierarchy'!E:E) -> Drywall Hand Tools | F54: =_xlfn.XLOOKUP(B54,'Product Hierarchy'!A:A,'Product Hierarchy'!F:F) -> Hawks | G54: 52.49 | H54: 47.24 | I54: 33.07 | J54: Each | K54: 4 | L54: 4 | N54: =M54*I54 -> 0
A55: 450069 | B55: DXTT-2-326 | C55: DEWALT Hawk 16" x 16" | D55: =_xlfn.XLOOKUP(B55,'Product Hierarchy'!A:A,'Product Hierarchy'!C:C) -> DEWALT | E55: =_xlfn.XLOOKUP(B55,'Product Hierarchy'!A:A,'Product Hierarchy'!E:E) -> Drywall Hand Tools | F55: =_xlfn.XLOOKUP(B55,'Product Hierarchy'!A:A,'Product Hierarchy'!F:F) -> Hawks | G55: 63.99 | H55: 57.59 | I55: 40.31 | J55: Each | K55: 1 | L55: 4 | N55: =M55*I55 -> 0
A56: 450326 | B56: DXTT-7-332 | C56: DEWALT 12"SS Mud Pan | D56: =_xlfn.XLOOKUP(B56,'Product Hierarchy'!A:A,'Product Hierarchy'!C:C) -> DEWALT | E56: =_xlfn.XLOOKUP(B56,'Product Hierarchy'!A:A,'Product Hierarchy'!E:E) -> Drywall Hand Tools | F56: =_xlfn.XLOOKUP(B56,'Product Hierarchy'!A:A,'Product Hierarchy'!F:F) -> Mud Pans | G56: 26.49 | H56: 23.84 | I56: 16.69 | J56: Each | K56: 6 | L56: 12 | N56: =M56*I56 -> 0
A57: 450071 | B57: DXTT-2-334 | C57: DEWALT 14"SS Mud Pan | D57: =_xlfn.XLOOKUP(B57,'Product Hierarchy'!A:A,'Product Hierarchy'!C:C) -> DEWALT | E57: =_xlfn.XLOOKUP(B57,'Product Hierarchy'!A:A,'Product Hierarchy'!E:E) -> Drywall Hand Tools | F57: =_xlfn.XLOOKUP(B57,'Product Hierarchy'!A:A,'Product Hierarchy'!F:F) -> Mud Pans | G57: 27.99 | H57: 25.19 | I57: 17.63 | J57: Each | K57: 6 | L57: 12 | N57: =M57*I57 -> 0
... A84: 450098 | B84: DXTT-2-411 | C84: DEWALT Welded Joint Knife Grips 5Pk | D84: =_xlfn.XLOOKUP(B84,'Product Hierarchy'!A:A,'Product Hierarchy'!C:C) -> DEWALT | E84: =_xlfn.XLOOKUP(B84,'Product Hierarchy'!A:A,'Product Hierarchy'!E:E) -> Drywall Hand Tools | F84: =_xlfn.XLOOKUP(B84,'Product Hierarchy'!A:A,'Product Hierarchy'!F:F) -> Joint Knives | G84: 8.99 | H84: 8.09 | I84: 5.66 | J84: Each | K84: 24 | L84: 144 | N84: =M84*I84 -> 0
A85: 450099 | B85: DXTT-2-414 | C85: DW 8" SS TAPING KNIFE - W/WELDED HNDL | D85: DEWALT | E85: Drywall Hand Tools | F85: Taping Knives | G85: 20.99 | H85: 18.89 | I85: 13.22 | J85: Each | K85: 4 | L85: 24 | N85: =M85*I85 -> 0
A86: 450100 | B86: DXTT-2-416 | C86: DW 10" SS TAPING KNIFE - W/WELDED HNDL | D86: DEWALT | E86: Drywall Hand Tools | F86: Taping Knives | G86: 21.99 | H86: 19.79 | I86: 13.85 | J86: Each | K86: 4 | L86: 24 | N86: =M86*I86 -> 0
A87: 450101 | B87: DXTT-2-417 | C87: DW 12" SS TAPING KNIFE - W/WELDED HNDL | D87: DEWALT | E87: Drywall Hand Tools | F87: Taping Knives | G87: 22.99 | H87: 20.69 | I87: 14.48 | J87: Each | K87: 4 | L87: 24 | N87: =M87*I87 -> 0
A88: 450102 | B88: DXTT-2-418 | C88: DW 14" SS TAPING KNIFE - W/WELDED HNDL | D88: DEWALT | E88: Drywall Hand Tools | F88: Taping Knives | G88: 23.99 | H88: 21.59 | I88: 15.11 | J88: Each | K88: 4 | L88: 24 | N88: =M88*I88 -> 0
A89: 450103 | B89: DXTT-2-420 | C89: DEWALT 4" SS Stretch Joint Knife | D89: =_xlfn.XLOOKUP(B89,'Product Hierarchy'!A:A,'Product Hierarchy'!C:C) -> DEWALT | E89: =_xlfn.XLOOKUP(B89,'Product Hierarchy'!A:A,'Product Hierarchy'!E:E) -> Drywall Hand Tools | F89: =_xlfn.XLOOKUP(B89,'Product Hierarchy'!A:A,'Product Hierarchy'!F:F) -> Joint Knives | G89: 25.99 | H89: 23.39 | I89: 16.37 | J89: Each | K89: 8 | L89: 48 | N89: =M89*I89 -> 0
A90: 450104 | B90: DXTT-2-421 | C90: DEWALT 5" SS Stretch Joint Knife | D90: =_xlfn.XLOOKUP(B90,'Product Hierarchy'!A:A,'Product Hierarchy'!C:C) -> DEWALT | E90: =_xlfn.XLOOKUP(B90,'Product Hierarchy'!A:A,'Product Hierarchy'!E:E) -> Drywall Hand Tools | F90: =_xlfn.XLOOKUP(B90,'Product Hierarchy'!A:A,'Product Hierarchy'!F:F) -> Joint Knives | G90: 26.99 | H90: 24.29 | I90: 17 | J90: Each | K90: 8 | L90: 48 | N90: =M90*I90 -> 0
A91: 450105 | B91: DXTT-2-422 | C91: DEWALT 6" SS Stretch Joint Knife | D91: =_xlfn.XLOOKUP(B91,'Product Hierarchy'!A:A,'Product Hierarchy'!C:C) -> DEWALT | E91: =_xlfn.XLOOKUP(B91,'Product Hierarchy'!A:A,'Product Hierarchy'!E:E) -> Drywall Hand Tools | F91: =_xlfn.XLOOKUP(B91,'Product Hierarchy'!A:A,'Product Hierarchy'!F:F) -> Joint Knives | G91: 28.49 | H91: 25.64 | I91: 17.95 | J91: Each | K91: 8 | L91: 48 | N91: =M91*I91 -> 0
A92: 450106 | B92: DXTT-2-423 | C92: DEWALT 8" SS Stretch Joint Knife | D92: =_xlfn.XLOOKUP(B92,'Product Hierarchy'!A:A,'Product Hierarchy'!C:C) -> DEWALT | E92: =_xlfn.XLOOKUP(B92,'Product Hierarchy'!A:A,'Product Hierarchy'!E:E) -> Drywall Hand Tools | F92: =_xlfn.XLOOKUP(B92,'Product Hierarchy'!A:A,'Product Hierarchy'!F:F) -> Joint Knives | G92: 29.49 | H92: 26.54 | I92: 18.58 | J92: Each | K92: 8 | L92: 48 | N92: =M92*I92 -> 0
A93: 450107 | B93: DXTT-2-504 | C93: DEWALT 4" SS Joint Knife Composite Hndl | D93: =_xlfn.XLOOKUP(B93,'Product Hierarchy'!A:A,'Product Hierarchy'!C:C) -> DEWALT | E93: =_xlfn.XLOOKUP(B93,'Product Hierarchy'!A:A,'Product Hierarchy'!E:E) -> Drywall Hand Tools | F93: =_xlfn.XLOOKUP(B93,'Product Hierarchy'!A:A,'Product Hierarchy'!F:F) -> Joint Knives | G93: 14.49 | H93: 13.04 | I93: 9.13 | J93: Each | K93: 8 | L93: 48 | N93: =M93*I93 -> 0
A94: 450108 | B94: DXTT-2-505 | C94: DEWALT 5" SS Joint Knife Composite Hndl | D94: =_xlfn.XLOOKUP(B94,'Product Hierarchy'!A:A,'Product Hierarchy'!C:C) -> DEWALT | E94: =_xlfn.XLOOKUP(B94,'Product Hierarchy'!A:A,'Product Hierarchy'!E:E) -> Drywall Hand Tools | F94: =_xlfn.XLOOKUP(B94,'Product Hierarchy'!A:A,'Product Hierarchy'!F:F) -> Joint Knives | G94: 15.49 | H94: 13.94 | I94: 9.76 | J94: Each | K94: 8 | L94: 48 | N94: =M94*I94 -> 0
A95: 450109 | B95: DXTT-2-506 | C95: DEWALT 6" SS Joint Knife Composite Hndl | D95: =_xlfn.XLOOKUP(B95,'Product Hierarchy'!A:A,'Product Hierarchy'!C:C) -> DEWALT | E95: =_xlfn.XLOOKUP(B95,'Product Hierarchy'!A:A,'Product Hierarchy'!E:E) -> Drywall Hand Tools | F95: =_xlfn.XLOOKUP(B95,'Product Hierarchy'!A:A,'Product Hierarchy'!F:F) -> Joint Knives | G95: 16.49 | H95: 14.84 | I95: 10.39 | J95: Each | K95: 8 | L95: 48 | N95: =M95*I95 -> 0
A96: 450111 | B96: DXTT-2-600P | C96: DEWALT Pro Tap-Fin Set w/M Ext Hndls-P | D96: =_xlfn.XLOOKUP(B96,'Product Hierarchy'!A:A,'Product Hierarchy'!C:C) -> DEWALT | E96: =_xlfn.XLOOKUP(B96,'Product Hierarchy'!A:A,'Product Hierarchy'!E:E) -> Drywall Auto Tools | F96: =_xlfn.XLOOKUP(B96,'Product Hierarchy'!A:A,'Product Hierarchy'!F:F) -> Auto Tool Sets | G96: 6313.36 | H96: 5050.69 | I96: 3535.48 | J96: Each | K96: 1 | L96: 1 | N96: =M96*I96 -> 0
A97: 450118 | B97: DXTT-2-605 | C97: DEWALT Flat Box Set 10"/12"w/M Ext Hndl | D97: =_xlfn.XLOOKUP(B97,'Product Hierarchy'!A:A,'Product Hierarchy'!C:C) -> DEWALT | E97: =_xlfn.XLOOKUP(B97,'Product Hierarchy'!A:A,'Product Hierarchy'!E:E) -> Drywall Auto Tools | F97: =_xlfn.XLOOKUP(B97,'Product Hierarchy'!A:A,'Product Hierarchy'!F:F) -> Auto Tool Sets | G97: 1816.46 | H97: 1453.17 | I97: 1017.22 | J97: Each | K97: 1 | L97: 1 | N97: =M97*I97 -> 0
A98: 450125 | B98: DXTT-2-615 | C98: DEWALT MEGA Set 10"/12"w/40"-62"Ext Hndl | D98: =_xlfn.XLOOKUP(B98,'Product Hierarchy'!A:A,'Product Hierarchy'!C:C) -> DEWALT | E98: =_xlfn.XLOOKUP(B98,'Product Hierarchy'!A:A,'Product Hierarchy'!E:E) -> Drywall Auto Tools | F98: =_xlfn.XLOOKUP(B98,'Product Hierarchy'!A:A,'Product Hierarchy'!F:F) -> Auto Tool Sets | G98: 1866.46 | H98: 1493.17 | I98: 1045.22 | J98: Each | K98: 1 | L98: 1 | N98: =M98*I98 -> 0
A99: 450127 | B99: DXTT-2-616P | C99: DEWALT MEGA Pro Taping Set w/MExtHndls-P | D99: =_xlfn.XLOOKUP(B99,'Product Hierarchy'!A:A,'Product Hierarchy'!C:C) -> DEWALT | E99: =_xlfn.XLOOKUP(B99,'Product Hierarchy'!A:A,'Product Hierarchy'!E:E) -> Drywall Auto Tools | F99: =_xlfn.XLOOKUP(B99,'Product Hierarchy'!A:A,'Product Hierarchy'!F:F) -> Auto Tool Sets | G99: 6363.36 | H99: 5090.69 | I99: 3563.48 | J99: Each | K99: 1 | L99: 1 | N99: =M99*I99 -> 0
A100: 450132 | B100: DXTT-2-701 | C100: DEWALT 7"Corner Applicator | D100: =_xlfn.XLOOKUP(B100,'Product Hierarchy'!A:A,'Product Hierarchy'!C:C) -> DEWALT | E100: =_xlfn.XLOOKUP(B100,'Product Hierarchy'!A:A,'Product Hierarchy'!E:E) -> Drywall Auto Tools | F100: =_xlfn.XLOOKUP(B100,'Product Hierarchy'!A:A,'Product Hierarchy'!F:F) -> Applicator Boxes | G100: 335.99 | H100: 285.59 | I100: 199.91 | J100: Each | K100: 1 | L100: 6 | N100: =M100*I100 -> 0
... A140: 450178 | B140: DXTT-2-924 | C140: DEWALT 24"Skimming Blade | D140: =_xlfn.XLOOKUP(B140,'Product Hierarchy'!A:A,'Product Hierarchy'!C:C) -> DEWALT | E140: =_xlfn.XLOOKUP(B140,'Product Hierarchy'!A:A,'Product Hierarchy'!E:E) -> Drywall Semi Auto Tools | F140: =_xlfn.XLOOKUP(B140,'Product Hierarchy'!A:A,'Product Hierarchy'!F:F) -> Skimming Blades | G140: 119.49 | H140: 107.54 | I140: 75.28 | J140: Each | K140: 1 | L140: 4 | N140: =M140*I140 -> 0
A141: 450179 | B141: DXTT-2-924C | C141: DEWALT 24" Composite Skimming Blade | D141: DEWALT | E141: Drywall Semi Auto Tools | F141: Skimming Blades | G141: 69.99 | H141: 62.99 | I141: 44.09 | J141: Each | K141: 2 | L141: 4 | N141: =M141*I141 -> 0
A142: 450180 | B142: DXTT-2-932 | C142: DEWALT 32"Skimming Blade | D142: =_xlfn.XLOOKUP(B142,'Product Hierarchy'!A:A,'Product Hierarchy'!C:C) -> DEWALT | E142: =_xlfn.XLOOKUP(B142,'Product Hierarchy'!A:A,'Product Hierarchy'!E:E) -> Drywall Semi Auto Tools | F142: =_xlfn.XLOOKUP(B142,'Product Hierarchy'!A:A,'Product Hierarchy'!F:F) -> Skimming Blades | G142: 160.49 | H142: 144.44 | I142: 101.11 | J142: Each | K142: 1 | L142: 4 | N142: =M142*I142 -> 0
A143: 450182 | B143: DXTT-2-940 | C143: DEWALT 40"Skimming Blade | D143: =_xlfn.XLOOKUP(B143,'Product Hierarchy'!A:A,'Product Hierarchy'!C:C) -> DEWALT | E143: =_xlfn.XLOOKUP(B143,'Product Hierarchy'!A:A,'Product Hierarchy'!E:E) -> Drywall Semi Auto Tools | F143: =_xlfn.XLOOKUP(B143,'Product Hierarchy'!A:A,'Product Hierarchy'!F:F) -> Skimming Blades | G143: 180.99 | H143: 162.89 | I143: 114.02 | J143: Each | K143: 1 | L143: 6 | N143: =M143*I143 -> 0
A144: 450183 | B144: DXTT-2-941 | C144: DEWALT Skimming Blade Adapter | D144: =_xlfn.XLOOKUP(B144,'Product Hierarchy'!A:A,'Product Hierarchy'!C:C) -> DEWALT | E144: =_xlfn.XLOOKUP(B144,'Product Hierarchy'!A:A,'Product Hierarchy'!E:E) -> Drywall Semi Auto Tools | F144: =_xlfn.XLOOKUP(B144,'Product Hierarchy'!A:A,'Product Hierarchy'!F:F) -> Handles | G144: 49.49 | H144: 44.54 | I144: 31.18 | J144: Each | K144: 6 | L144: 24 | N144: =M144*I144 -> 0
A145: 450184 | B145: DXTT-2-942 | C145: DEWALT 37"-63"Skimming Blade Ext Hndl | D145: =_xlfn.XLOOKUP(B145,'Product Hierarchy'!A:A,'Product Hierarchy'!C:C) -> DEWALT | E145: =_xlfn.XLOOKUP(B145,'Product Hierarchy'!A:A,'Product Hierarchy'!E:E) -> Drywall Semi Auto Tools | F145: =_xlfn.XLOOKUP(B145,'Product Hierarchy'!A:A,'Product Hierarchy'!F:F) -> Handles | G145: 63.49 | H145: 57.14 | I145: 40 | J145: Each | K145: 6 | L145: 24 | N145: =M145*I145 -> 0
A146: 450185 | B146: DXTT-2-943 | C146: DEWALT 48"-87"Skimming Blade Ext Hndl | D146: =_xlfn.XLOOKUP(B146,'Product Hierarchy'!A:A,'Product Hierarchy'!C:C) -> DEWALT | E146: =_xlfn.XLOOKUP(B146,'Product Hierarchy'!A:A,'Product Hierarchy'!E:E) -> Drywall Semi Auto Tools | F146: =_xlfn.XLOOKUP(B146,'Product Hierarchy'!A:A,'Product Hierarchy'!F:F) -> Handles | G146: 77.49 | H146: 69.74 | I146: 48.82 | J146: Each | K146: 6 | L146: 24 | N146: =M146*I146 -> 0
A147: 450187 | B147: DXTT-2-945 | C147: DEWALT 37"-63"Skimming Blade Hndl w/Adpt | D147: =_xlfn.XLOOKUP(B147,'Product Hierarchy'!A:A,'Product Hierarchy'!C:C) -> DEWALT | E147: =_xlfn.XLOOKUP(B147,'Product Hierarchy'!A:A,'Product Hierarchy'!E:E) -> Drywall Semi Auto Tools | F147: =_xlfn.XLOOKUP(B147,'Product Hierarchy'!A:A,'Product Hierarchy'!F:F) -> Skimming Blade Sets | G147: 112.98 | H147: 96.03 | I147: 67.22 | J147: Each | K147: 1 | L147: 1 | N147: =M147*I147 -> 0
A148: 450188 | B148: DXTT-2-948 | C148: DEWALT 48"Skimming Blade | D148: =_xlfn.XLOOKUP(B148,'Product Hierarchy'!A:A,'Product Hierarchy'!C:C) -> DEWALT | E148: =_xlfn.XLOOKUP(B148,'Product Hierarchy'!A:A,'Product Hierarchy'!E:E) -> Drywall Semi Auto Tools | F148: =_xlfn.XLOOKUP(B148,'Product Hierarchy'!A:A,'Product Hierarchy'!F:F) -> Skimming Blades | G148: 247.49 | H148: 222.74 | I148: 155.92 | J148: Each | K148: 1 | L148: 6 | N148: =M148*I148 -> 0
A149: 450189 | B149: DXTT-2-949 | C149: DEWALT 7"Skimming Blade Insert | D149: =_xlfn.XLOOKUP(B149,'Product Hierarchy'!A:A,'Product Hierarchy'!C:C) -> DEWALT | E149: =_xlfn.XLOOKUP(B149,'Product Hierarchy'!A:A,'Product Hierarchy'!E:E) -> Drywall Semi Auto Tools | F149: =_xlfn.XLOOKUP(B149,'Product Hierarchy'!A:A,'Product Hierarchy'!F:F) -> Skimming Blades | G149: 19.49 | H149: 17.54 | I149: 12.28 | J149: Each | K149: 1 | L149: 24 | N149: =M149*I149 -> 0
A150: 450190 | B150: DXTT-2-950 | C150: DEWALT 14"Skimming Blade Insert | D150: =_xlfn.XLOOKUP(B150,'Product Hierarchy'!A:A,'Product Hierarchy'!C:C) -> DEWALT | E150: =_xlfn.XLOOKUP(B150,'Product Hierarchy'!A:A,'Product Hierarchy'!E:E) -> Drywall Semi Auto Tools | F150: =_xlfn.XLOOKUP(B150,'Product Hierarchy'!A:A,'Product Hierarchy'!F:F) -> Skimming Blades | G150: 31.49 | H150: 28.34 | I150: 19.84 | J150: Each | K150: 1 | L150: 24 | N150: =M150*I150 -> 0
A151: 450191 | B151: DXTT-2-951 | C151: DEWALT 10"Skimming Blade Insert | D151: =_xlfn.XLOOKUP(B151,'Product Hierarchy'!A:A,'Product Hierarchy'!C:C) -> DEWALT | E151: =_xlfn.XLOOKUP(B151,'Product Hierarchy'!A:A,'Product Hierarchy'!E:E) -> Drywall Semi Auto Tools | F151: =_xlfn.XLOOKUP(B151,'Product Hierarchy'!A:A,'Product Hierarchy'!F:F) -> Skimming Blades | G151: 25.99 | H151: 23.39 | I151: 16.37 | J151: Each | K151: 1 | L151: 24 | N151: =M151*I151 -> 0
A152: 450192 | B152: DXTT-2-952 | C152: DEWALT 16"Skimming Blade Insert | D152: =_xlfn.XLOOKUP(B152,'Product Hierarchy'!A:A,'Product Hierarchy'!C:C) -> DEWALT | E152: =_xlfn.XLOOKUP(B152,'Product Hierarchy'!A:A,'Product Hierarchy'!E:E) -> Drywall Semi Auto Tools | F152: =_xlfn.XLOOKUP(B152,'Product Hierarchy'!A:A,'Product Hierarchy'!F:F) -> Skimming Blades | G152: 33.49 | H152: 30.14 | I152: 21.1 | J152: Each | K152: 1 | L152: 24 | N152: =M152*I152 -> 0
A153: 450193 | B153: DXTT-2-953 | C153: DEWALT 24"Skimming Blade Insert | D153: =_xlfn.XLOOKUP(B153,'Product Hierarchy'!A:A,'Product Hierarchy'!C:C) -> DEWALT | E153: =_xlfn.XLOOKUP(B153,'Product Hierarchy'!A:A,'Product Hierarchy'!E:E) -> Drywall Semi Auto Tools | F153: =_xlfn.XLOOKUP(B153,'Product Hierarchy'!A:A,'Product Hierarchy'!F:F) -> Skimming Blades | G153: 40.99 | H153: 36.89 | I153: 25.82 | J153: Each | K153: 1 | L153: 24 | N153: =M153*I153 -> 0
... A212: 450324 | B212: DXTT-7-142 | C212: DEWALT 6"SS Joint Knife-Sft Grp Hndl | D212: =_xlfn.XLOOKUP(B212,'Product Hierarchy'!A:A,'Product Hierarchy'!C:C) -> DEWALT | E212: =_xlfn.XLOOKUP(B212,'Product Hierarchy'!A:A,'Product Hierarchy'!E:E) -> Drywall Hand Tools | F212: =_xlfn.XLOOKUP(B212,'Product Hierarchy'!A:A,'Product Hierarchy'!F:F) -> Joint Knives | G212: 18.49 | H212: 16.64 | I212: 11.65 | J212: Each | K212: 8 | L212: 48 | N212: =M212*I212 -> 0
J213: DeWalt Totals: | M213: =SUM(M11:M212) -> 0 | N213: =SUM(N11:N212) -> 0

Sheet Order Input-Individual Part 
F1: Order Form
A3: Customer: | C3: ='Order Summary'!B3 -> 0 | J3: Order date: | L3: ='Order Summary'!F3 -> 0
A4: Ship To: | C4: ='Order Summary'!B4 -> 0 | J4: PO#: | L4: ='Order Summary'!F4 -> 0
A5: ='Order Summary'!B5 -> 0 | J5: Need by date: | L5: ='Order Summary'!F5 -> 0
A6: ='Order Summary'!B6 -> 0 | J6: Carrier: | L6: ='Order Summary'!F6 -> 0
A7: ALL PARTS SALES ARE FINAL
A8: Part # | B8: Sku # | C8: Description | D8: Brand | E8: Product Group | F8: Product Type | G8: MSRP | H8: MAPP | I8: Your Price | J8: UOM | K8: Order Quantity | L8: Total Price
A9: TAPER PARTS
A10: 449209 | B10: 7001 | C10: Handle Outlet Valve | D10: LEVEL5 | E10: Drywall Auto Tools | F10: Parts | G10: 37.99 | H10: 32.29 | I10: 22.6 | J10: Each | L10: =K10*I10 -> 0
A11: 449210 | B11: 7002 | C11: Wiper, Control Valve | D11: LEVEL5 | E11: Drywall Auto Tools | F11: Parts | G11: 5.49 | H11: 4.67 | I11: 3.27 | J11: Each | L11: =K11*I11 -> 0
A12: 448572 | B12: 7005 | C12: Lock Roller Assembly (Brake) | D12: LEVEL5 | E12: Drywall Auto Tools | F12: Parts | G12: 15.49 | H12: 13.17 | I12: 9.22 | J12: Each | L12: =K12*I12 -> 0
A13: 448579 | B13: 7035 | C13: Anvil | D13: LEVEL5 | E13: Drywall Auto Tools | F13: Parts | G13: 18.49 | H13: 15.72 | I13: 11 | J13: Each | L13: =K13*I13 -> 0
A14: 448583 | B14: 7040 | C14: Needle Gooser | D14: LEVEL5 | E14: Drywall Auto Tools | F14: Parts | G14: 1.99 | H14: 1.69 | I14: 1.18 | J14: Each | L14: =K14*I14 -> 0
A15: 448589 | B15: 7059 | C15: Creaser Wheel | D15: LEVEL5 | E15: Drywall Auto Tools | F15: Parts | G15: 5.99 | H15: 5.09 | I15: 3.56 | J15: Each | L15: =K15*I15 -> 0
A16: 448438 | B16: 7063 | C16: Bearing Nyliner | D16: LEVEL5 | E16: Drywall Auto Tools | F16: Parts | G16: 2.49 | H16: 2.12 | I16: 1.48 | J16: Each | L16: =K16*I16 -> 0
A17: 448956 | B17: 7069 | C17: 8-32 x 5/16 Setscrew | D17: LEVEL5 | E17: Drywall Auto Tools | F17: Parts | G17: 3.99 | H17: 3.39 | I17: 2.37 | J17: Each | L17: =K17*I17 -> 0
A18: 448593 | B18: 7077 | C18: Taper Wheel | D18: LEVEL5 | E18: Drywall Auto Tools | F18: Parts | G18: 21.49 | H18: 18.27 | I18: 12.79 | J18: Each | L18: =K18*I18 -> 0
A19: 448966 | B19: 7094 | C19: Spring Drive Dog | D19: LEVEL5 | E19: Drywall Auto Tools | F19: Parts | G19: 3.49 | H19: 2.97 | I19: 2.08 | J19: Each | L19: =K19*I19 -> 0
A20: 448605 | B20: 7097 | C20: Drive Dog Assembly | D20: LEVEL5 | E20: Drywall Auto Tools | F20: Parts | G20: 150.49 | H20: 127.92 | I20: 89.54 | J20: Each | L20: =K20*I20 -> 0
A21: 448494 | B21: 7104 | C21: Main Chain | D21: LEVEL5 | E21: Drywall Auto Tools | F21: Parts | G21: 75.49 | H21: 64.17 | I21: 44.92 | J21: Each | L21: =K21*I21 -> 0
... A38: 449124 | B38: 9108 | C38: Cutter Spring- Taper | D38: LEVEL5 | E38: Drywall Auto Tools | F38: Parts | G38: 18.49 | H38: 15.72 | I38: 11 | J38: Each | L38: =K38*I38 -> 0
A39: PUMP PARTS
A40: 448670 | B40: 7323 | C40: Gland | D40: LEVEL5 | E40: Drywall Auto Tools | F40: Parts | G40: 36.49 | H40: 31.02 | I40: 21.71 | J40: Each | L40: =K40*I40 -> 0
A41: 449187 | B41: 7324 | C41: U-Seal | D41: LEVEL5 | E41: Drywall Auto Tools | F41: Parts | G41: 4.99 | H41: 4.24 | I41: 2.97 | J41: Each | L41: =K41*I41 -> 0
A42: 449022 | B42: 7326 | C42: 5/16-24 Hex Head | D42: LEVEL5 | E42: Drywall Auto Tools | F42: Parts | G42: 1.99 | H42: 1.69 | I42: 1.18 | J42: Each | L42: =K42*I42 -> 0
A43: 449024 | B43: 7328 | C43: Piston Cups | D43: LEVEL5 | E43: Drywall Auto Tools | F43: Parts | G43: 13.99 | H43: 11.89 | I43: 8.32 | J43: Each | L43: =K43*I43 -> 0
A44: 448671 | B44: 7329 | C44: Valve Disc | D44: LEVEL5 | E44: Drywall Auto Tools | F44: Parts | G44: 9.49 | H44: 8.07 | I44: 5.65 | J44: Each | L44: =K44*I44 -> 0
A45: 449177 | B45: 7350 | C45: Filler O'Ring | D45: LEVEL5 | E45: Drywall Auto Tools | F45: Parts | G45: 1.99 | H45: 1.69 | I45: 1.18 | J45: Each | L45: =K45*I45 -> 0
A46: 449029 | B46: 7352 | C46: 5-16-24 x 1 7/16 Std Screw | D46: LEVEL5 | E46: Drywall Auto Tools | F46: Parts | G46: 12.49 | H46: 10.62 | I46: 7.43 | J46: Each | L46: =K46*I46 -> 0
A47: 449030 | B47: 7353 | C47: Special Nut | D47: LEVEL5 | E47: Drywall Auto Tools | F47: Parts | G47: 12.49 | H47: 10.62 | I47: 7.43 | J47: Each | L47: =K47*I47 -> 0
A48: 448675 | B48: 7355 | C48: Filler Body | D48: LEVEL5 | E48: Drywall Auto Tools | F48: Parts | G48: 60.49 | H48: 51.42 | I48: 35.99 | J48: Each | L48: =K48*I48 -> 0
A49: 448676 | B49: 7356 | C49: Discharge Tube | D49: LEVEL5 | E49: Drywall Auto Tools | F49: Parts | G49: 30.49 | H49: 25.92 | I49: 18.14 | J49: Each | L49: =K49*I49 -> 0
A50: 448677 | B50: 7358 | C50: Chain Assembly (W/ 1 S Hook) | D50: LEVEL5 | E50: Drywall Auto Tools | F50: Parts | G50: 22.49 | H50: 19.12 | I50: 13.38 | J50: Each | L50: =K50*I50 -> 0
A51: 449188 | B51: 7362 | C51: Gooseneck Gasket | D51: LEVEL5 | E51: Drywall Auto Tools | F51: Parts | G51: 6.49 | H51: 5.52 | I51: 3.86 | J51: Each | L51: =K51*I51 -> 0
... A58: 448887 | B58: 9624 | C58: Pump Tube | D58: LEVEL5 | E58: Drywall Auto Tools | F58: Parts | G58: 180.49 | H58: 153.42 | I58: 107.39 | J58: Each | L58: =K58*I58 -> 0
A59: BOX PARTS
A60: 448441 | B60: 7119 | C60: Nylon Bearing-Straight | D60: LEVEL5 | E60: Drywall Auto Tools | F60: Parts | G60: 4.49 | H60: 3.82 | I60: 2.67 | J60: Each | L60: =K60*I60 -> 0
A61: 448634 | B61: 7207 | C61: 7" Flat Box Blade | D61: LEVEL5 | E61: Drywall Auto Tools | F61: Parts | G61: 4.99 | H61: 4.24 | I61: 2.97 | J61: Each | L61: =K61*I61 -> 0
A62: 448635 | B62: 7208 | C62: Blade Holder Assembly 7" | D62: LEVEL5 | E62: Drywall Auto Tools | F62: Parts | G62: 180.49 | H62: 153.42 | I62: 107.39 | J62: Each | L62: =K62*I62 -> 0
A63: 448636 | B63: 7212 | C63: Skid Cover Rt Side, Universal | D63: LEVEL5 | E63: Drywall Auto Tools | F63: Parts | G63: 3.49 | H63: 2.97 | I63: 2.08 | J63: Each | L63: =K63*I63 -> 0
A64: 448468 | B64: 7216 | C64: Crown Spring | D64: LEVEL5 | E64: Drywall Auto Tools | F64: Parts | G64: 9.49 | H64: 8.07 | I64: 5.65 | J64: Each | L64: =K64*I64 -> 0
A65: 448499 | B65: 7224 | C65: Repair Clip | D65: LEVEL5 | E65: Drywall Auto Tools | F65: Parts | G65: 1.99 | H65: 1.69 | I65: 1.18 | J65: Each | L65: =K65*I65 -> 0
A66: 448642 | B66: 7239 | C66: Skid Cover Left Side Universal | D66: LEVEL5 | E66: Drywall Auto Tools | F66: Parts | G66: 3.49 | H66: 2.97 | I66: 2.08 | J66: Each | L66: =K66*I66 -> 0
A67: 448648 | B67: 7254 | C67: 10" Flat Box Blade | D67: LEVEL5 | E67: Drywall Auto Tools | F67: Parts | G67: 7.99 | H67: 6.79 | I67: 4.75 | J67: Each | L67: =K67*I67 -> 0
A68: 448652 | B68: 7268 | C68: 10" Clamp Assembly Classic Box | D68: LEVEL5 | E68: Drywall Auto Tools | F68: Parts | G68: 37.99 | H68: 32.29 | I68: 22.6 | J68: Each | L68: =K68*I68 -> 0
A69: 448653 | B69: 7270 | C69: 12" Flat Box Blade | D69: LEVEL5 | E69: Drywall Auto Tools | F69: Parts | G69: 9.49 | H69: 8.07 | I69: 5.65 | J69: Each | L69: =K69*I69 -> 0
A70: 448654 | B70: 7273 | C70: 14" Flat Box Blade | D70: LEVEL5 | E70: Drywall Auto Tools | F70: Parts | G70: 10.99 | H70: 9.34 | I70: 6.54 | J70: Each | L70: =K70*I70 -> 0
A71: 448655 | B71: 7274 | C71: 14" Box Blade Holder Assembly | D71: LEVEL5 | E71: Drywall Auto Tools | F71: Parts | G71: 270.49 | H71: 229.92 | I71: 160.94 | J71: Each | L71: =K71*I71 -> 0
... A80: 448896 | B80: 9719 | C80: FB Box Wheel, Black | D80: LEVEL5 | E80: Drywall Auto Tools | F80: Parts | G80: 9.49 | H80: 8.07 | I80: 5.65 | J80: Each | L80: =K80*I80 -> 0
A81: CORNER FINISHER PARTS
A82: 448504 | B82: 7740 | C82: CF Lock Clip Spring | D82: LEVEL5 | E82: Drywall Auto Tools | F82: Parts | G82: 1.99 | H82: 1.69 | I82: 1.18 | J82: Each | L82: =K82*I82 -> 0
A83: 448505 | B83: 7741 | C83: CF Ball Locking Clip | D83: LEVEL5 | E83: Drywall Auto Tools | F83: Parts | G83: 25.99 | H83: 22.09 | I83: 15.46 | J83: Each | L83: =K83*I83 -> 0
A84: 448840 | B84: 9188 | C84: CF 3" Blade | D84: LEVEL5 | E84: Drywall Auto Tools | F84: Parts | G84: 37.99 | H84: 32.29 | I84: 22.6 | J84: Each | L84: =K84*I84 -> 0
A85: 448841 | B85: 9189 | C85: CF 2.5" and 3" Skid | D85: LEVEL5 | E85: Drywall Auto Tools | F85: Parts | G85: 22.99 | H85: 19.54 | I85: 13.68 | J85: Each | L85: =K85*I85 -> 0
A86: 449126 | B86: 9191 | C86: CF 6-32 x 1/8 SS Hex | D86: LEVEL5 | E86: Drywall Auto Tools | F86: Parts | G86: 1.99 | H86: 1.69 | I86: 1.18 | J86: Each | L86: =K86*I86 -> 0
A87: 448508 | B87: 9192 | C87: CF Bottom Clip 2.5" & 3" | D87: LEVEL5 | E87: Drywall Auto Tools | F87: Parts | G87: 16.99 | H87: 14.44 | I87: 10.11 | J87: Each | L87: =K87*I87 -> 0
A88: 448509 | B88: 9195 | C88: CF Top Clip | D88: LEVEL5 | E88: Drywall Auto Tools | F88: Parts | G88: 9.49 | H88: 8.07 | I88: 5.65 | J88: Each | L88: =K88*I88 -> 0
A89: 448510 | B89: 9196 | C89: CF Buttom Clip 3.5" & 4" | D89: LEVEL5 | E89: Drywall Auto Tools | F89: Parts | G89: 16.99 | H89: 14.44 | I89: 10.11 | J89: Each | L89: =K89*I89 -> 0
A90: 448511 | B90: 9197 | C90: CF Top Clip 3.5" & 4" | D90: LEVEL5 | E90: Drywall Auto Tools | F90: Parts | G90: 9.49 | H90: 8.07 | I90: 5.65 | J90: Each | L90: =K90*I90 -> 0
A91: 448537 | B91: 9512 | C91: CF Rubber Tire | D91: LEVEL5 | E91: Drywall Auto Tools | F91: Parts | G91: 1.99 | H91: 1.69 | I91: 1.18 | J91: Each | L91: =K91*I91 -> 0
A92: 448873 | B92: 9525 | C92: CF 3.5" & 4" Skids | D92: LEVEL5 | E92: Drywall Auto Tools | F92: Parts | G92: 24.49 | H92: 20.82 | I92: 14.57 | J92: Each | L92: =K92*I92 -> 0
A93: 448893 | B93: 9706 | C93: CF 2.5" Blade | D93: LEVEL5 | E93: Drywall Auto Tools | F93: Parts | G93: 27.49 | H93: 23.37 | I93: 16.36 | J93: Each | L93: =K93*I93 -> 0
... A95: 448902 | B95: 9816 | C95: 4" Blade-Corner Finisher | D95: LEVEL5 | E95: Drywall Auto Tools | F95: Parts | G95: 52.99 | H95: 45.04 | I95: 31.53 | J95: Each | L95: =K95*I95 -> 0
A96: APPLICATOR PARTS
A97: 449037 | B97: 7378 | C97: 5/16 - 18 3/4 Thumbscrew, SS | D97: LEVEL5 | E97: Drywall Auto Tools | F97: Parts | G97: 7.99 | H97: 6.79 | I97: 4.75 | J97: Each | L97: =K97*I97 -> 0
A98: 448446 | B98: 7409 | C98: Bearing, 5L7D-642 | D98: LEVEL5 | E98: Drywall Auto Tools | F98: Parts | G98: 3.49 | H98: 2.97 | I98: 2.08 | J98: Each | L98: =K98*I98 -> 0
A99: 448472 | B99: 7792 | C99: Latch | D99: LEVEL5 | E99: Drywall Auto Tools | F99: Parts | G99: 7.49 | H99: 6.37 | I99: 4.46 | J99: Each | L99: =K99*I99 -> 0
A100: 449200 | B100: 9312 | C100: Wiper Seal 7" | D100: LEVEL5 | E100: Drywall Auto Tools | F100: Parts | G100: 27.49 | H100: 23.37 | I100: 16.36 | J100: Each | L100: =K100*I100 -> 0
A101: 449201 | B101: 9313 | C101: 8" App. Gasket | D101: LEVEL5 | E101: Drywall Auto Tools | F101: Parts | G101: 27.49 | H101: 23.37 | I101: 16.36 | J101: Each | L101: =K101*I101 -> 0
A102: 448483 | B102: 9314 | C102: Corner Applicator Bracket | D102: LEVEL5 | E102: Drywall Auto Tools | F102: Parts | G102: 45.49 | H102: 38.67 | I102: 27.07 | J102: Each | L102: =K102*I102 -> 0
A103: 448859 | B103: 9317 | C103: Corner Applicator Cone | D103: LEVEL5 | E103: Drywall Auto Tools | F103: Parts | G103: 135.49 | H103: 115.17 | I103: 80.62 | J103: Each | L103: =K103*I103 -> 0
A104: EXT BOX HANDLE PARTS
A105: 448438 | B105: 7063 | C105: Bearing Nyliner | D105: LEVEL5 | E105: Drywall Auto Tools | F105: Parts | G105: 2.49 | H105: 2.12 | I105: 1.48 | J105: Each | L105: =K105*I105 -> 0
A106: 448804 | B106: 8405 | C106: Ext. Handle Lever | D106: LEVEL5 | E106: Drywall Auto Tools | F106: Parts | G106: 60.49 | H106: 51.42 | I106: 35.99 | J106: Each | L106: =K106*I106 -> 0
A107: 448455 | B107: 8515 | C107: Plastic Bearing | D107: LEVEL5 | E107: Drywall Auto Tools | F107: Parts | G107: 3.49 | H107: 2.97 | I107: 2.08 | J107: Each | L107: =K107*I107 -> 0
A108: 448456 | B108: 8516 | C108: Plastic Bearing | D108: LEVEL5 | E108: Drywall Auto Tools | F108: Parts | G108: 3.49 | H108: 2.97 | I108: 2.08 | J108: Each | L108: =K108*I108 -> 0
A109: 448817 | B109: 8519 | C109: EXT Box Handle Brake Assembly | D109: LEVEL5 | E109: Drywall Auto Tools | F109: Parts | G109: 37.99 | H109: 32.29 | I109: 22.6 | J109: Each | L109: =K109*I109 -> 0
A110: 449118 | B110: 8700 | C110: Drive Dog Set Screw - SS 8-32 x 3/16" | D110: LEVEL5 | E110: Drywall Auto Tools | F110: Parts | G110: 7.99 | H110: 6.79 | I110: 4.75 | J110: Each | L110: =K110*I110 -> 0
A111: 448845 | B111: 9212 | C111: Ext. Box Handle Head | D111: LEVEL5 | E111: Drywall Auto Tools | F111: Parts | G111: 142.99 | H111: 121.54 | I111: 85.08 | J111: Each | L111: =K111*I111 -> 0
A112: 448907 | B112: 9903 | C112: EH- Handle Head to Plate Connector | D112: LEVEL5 | E112: Drywall Auto Tools | F112: Parts | G112: 7.99 | H112: 6.79 | I112: 4.75 | J112: Each | L112: =K112*I112 -> 0
A113: ACC. HANDLE PARTS
A114: 449038 | B114: 7379 | C114: Small Thumb Screw | D114: LEVEL5 | E114: Drywall Auto Tools | F114: Parts | G114: 2.49 | H114: 2.12 | I114: 1.48 | J114: Each | L114: =K114*I114 -> 0
A115: NAIL SPOTTER PARTS
A116: 448663 | B116: 7290 | C116: 2" Nail Spotter Blade | D116: LEVEL5 | E116: Drywall Auto Tools | F116: Parts | G116: 18.49 | H116: 15.72 | I116: 11 | J116: Each | L116: =K116*I116 -> 0
A117: 448690 | B117: 7454 | C117: 3 Nail Spotter Blade | D117: LEVEL5 | E117: Drywall Auto Tools | F117: Parts | G117: 19.99 | H117: 16.99 | I117: 11.89 | J117: Each | L117: =K117*I117 -> 0
A118: 448714 | B118: 7727 | C118: 2" Wiper | D118: LEVEL5 | E118: Drywall Auto Tools | F118: Parts | G118: 25.99 | H118: 22.09 | I118: 15.46 | J118: Each | L118: =K118*I118 -> 0
A119: 448719 | B119: 7734 | C119: 3" Wiper | D119: LEVEL5 | E119: Drywall Auto Tools | F119: Parts | G119: 15.49 | H119: 13.17 | I119: 9.22 | J119: Each | L119: =K119*I119 -> 0
A120: MUDSHOT PARTS
A121: 448912 | B121: DXTT-1109 | C121: MudShot U-Cup | D121: DEWALT | E121: Drywall Auto Tools | F121: Parts | G121: 9.49 | H121: 8.07 | I121: 5.65 | J121: Each | L121: =K121*I121 -> 0
A122: 448913 | B122: DXTT-1111 | C122: Clear Tube Base | D122: DEWALT | E122: Drywall Auto Tools | F122: Parts | G122: 42.49 | H122: 36.12 | I122: 25.28 | J122: Each | L122: =K122*I122 -> 0
A123: 449183 | B123: DXTT-1117 | C123: Top Cone O'Ring | D123: DEWALT | E123: Drywall Auto Tools | F123: Parts | G123: 2.49 | H123: 2.12 | I123: 1.48 | J123: Each | L123: =K123*I123 -> 0
A124: 448516 | B124: DXTT-1125 | C124: Top Cone (Plastic Part Only) | D124: DEWALT | E124: Drywall Auto Tools | F124: Parts | G124: 30.49 | H124: 25.92 | I124: 18.14 | J124: Each | L124: =K124*I124 -> 0
A125: 449166 | B125: DXTT-1126 | C125: Screw | D125: DEWALT | E125: Drywall Auto Tools | F125: Parts | G125: 1.99 | H125: 1.69 | I125: 1.18 | J125: Each | L125: =K125*I125 -> 0
A126: 448920 | B126: DXTT-1132 | C126: MudShot Plunger U-Cup | D126: DEWALT | E126: Drywall Auto Tools | F126: Parts | G126: 22.99 | H126: 19.54 | I126: 13.68 | J126: Each | L126: =K126*I126 -> 0
A127: 448921 | B127: DXTT-1133 | C127: MudShot Plunger | D127: DEWALT | E127: Drywall Auto Tools | F127: Parts | G127: 30.49 | H127: 25.92 | I127: 18.14 | J127: Each | L127: =K127*I127 -> 0
A128: 449208 | B128: DXTT-1134 | C128: MudShot Cylinder Rod | D128: DEWALT | E128: Drywall Auto Tools | F128: Parts | G128: 150.49 | H128: 127.92 | I128: 89.54 | J128: Each | L128: =K128*I128 -> 0
A129: 448492 | B129: DXTT-1137 | C129: MudShot Gas Cylinder | D129: DEWALT | E129: Drywall Auto Tools | F129: Parts | G129: 135.49 | H129: 115.17 | I129: 80.62 | J129: Each | L129: =K129*I129 -> 0
A130: 448922 | B130: DXTT-1139 | C130: MudShot Cone Assembly | D130: DEWALT | E130: Drywall Auto Tools | F130: Parts | G130: 300.49 | H130: 255.42 | I130: 178.79 | J130: Each | L130: =K130*I130 -> 0
A131: 448923 | B131: DXTT-1140 | C131: Mud Shot Tube Assembly | D131: DEWALT | E131: Drywall Auto Tools | F131: Parts | G131: 412.99 | H131: 351.04 | I131: 245.73 | J131: Each | L131: =K131*I131 -> 0
A132: 448512 | B132: 9623 | C132: New pump latches | D132: LEVEL5 | E132: Drywall Auto Tools | F132: Parts | G132: 30.49 | H132: 25.92 | I132: 18.14 | J132: Each | L132: =K132*I132 -> 0
...

Sheet Order Input-Part Kits
F1: Order Form
A3: Customer: | C3: ='Order Summary'!B3 -> 0 | J3: Order date: | L3: ='Order Summary'!F3 -> 0
A4: Ship To: | C4: ='Order Summary'!B4 -> 0 | J4: PO#: | L4: ='Order Summary'!F4 -> 0
A5: ='Order Summary'!B5 -> 0 | J5: Need by date: | L5: ='Order Summary'!F5 -> 0
A6: ='Order Summary'!B6 -> 0 | J6: Carrier: | L6: ='Order Summary'!F6 -> 0
A7: ALL PARTS SALES ARE FINAL
A8: Part # | B8: Sku # | C8: Description | D8: Brand | E8: Product Group | F8: Product Type | G8: MSRP | H8: MAPP | I8: Your Price | J8: UOM | K8: Order Quantity | L8: Total Price
A9: 449578 | B9: 4-800 | C9: Pump Repair Kit | D9: =_xlfn.XLOOKUP(B9,'Product Hierarchy'!A:A,'Product Hierarchy'!C:C) -> LEVEL5 | E9: =_xlfn.XLOOKUP(B9,'Product Hierarchy'!A:A,'Product Hierarchy'!E:E) -> Drywall Auto Tools | F9: =_xlfn.XLOOKUP(B9,'Product Hierarchy'!A:A,'Product Hierarchy'!F:F) -> Repair Kits | G9: 45.92 | H9: 36.74 | I9: 25.72 | J9: Each | L9: =K9*I9 -> 0
A10: 449579 | B10: 4-801 | C10: Pump Rebuild Kit | D10: =_xlfn.XLOOKUP(B10,'Product Hierarchy'!A:A,'Product Hierarchy'!C:C) -> LEVEL5 | E10: =_xlfn.XLOOKUP(B10,'Product Hierarchy'!A:A,'Product Hierarchy'!E:E) -> Drywall Auto Tools | F10: =_xlfn.XLOOKUP(B10,'Product Hierarchy'!A:A,'Product Hierarchy'!F:F) -> Repair Kits | G10: 41.45 | H10: 33.16 | I10: 23.21 | J10: Each | L10: =K10*I10 -> 0
A11: 448546 | B11: 4-802 | C11: Ext. Box Handle Brake Assembly | D11: =_xlfn.XLOOKUP(B11,'Product Hierarchy'!A:A,'Product Hierarchy'!C:C) -> LEVEL5 | E11: =_xlfn.XLOOKUP(B11,'Product Hierarchy'!A:A,'Product Hierarchy'!E:E) -> Drywall Auto Tools | F11: =_xlfn.XLOOKUP(B11,'Product Hierarchy'!A:A,'Product Hierarchy'!F:F) -> Parts | G11: 44.46 | H11: 37.79 | I11: 26.45 | J11: Each | L11: =K11*I11 -> 0
A12: 449580 | B12: 4-803 | C12: Cleaning Kit | D12: =_xlfn.XLOOKUP(B12,'Product Hierarchy'!A:A,'Product Hierarchy'!C:C) -> LEVEL5 | E12: =_xlfn.XLOOKUP(B12,'Product Hierarchy'!A:A,'Product Hierarchy'!E:E) -> Drywall Auto Tools | F12: =_xlfn.XLOOKUP(B12,'Product Hierarchy'!A:A,'Product Hierarchy'!F:F) -> Repair Kits | G12: 99.46 | H12: 79.57 | I12: 55.7 | J12: Each | L12: =K12*I12 -> 0
A13: 449581 | B13: 4-805 | C13: 7" Flat Box Seal | D13: =_xlfn.XLOOKUP(B13,'Product Hierarchy'!A:A,'Product Hierarchy'!C:C) -> LEVEL5 | E13: =_xlfn.XLOOKUP(B13,'Product Hierarchy'!A:A,'Product Hierarchy'!E:E) -> Drywall Auto Tools | F13: =_xlfn.XLOOKUP(B13,'Product Hierarchy'!A:A,'Product Hierarchy'!F:F) -> Repair Kits | G13: 42.49 | H13: 33.99 | I13: 23.79 | J13: Each | L13: =K13*I13 -> 0
A14: 449184 | B14: 4-806 | C14: 10" Flat Box Seal | D14: =_xlfn.XLOOKUP(B14,'Product Hierarchy'!A:A,'Product Hierarchy'!C:C) -> LEVEL5 | E14: =_xlfn.XLOOKUP(B14,'Product Hierarchy'!A:A,'Product Hierarchy'!E:E) -> Drywall Auto Tools | F14: =_xlfn.XLOOKUP(B14,'Product Hierarchy'!A:A,'Product Hierarchy'!F:F) -> Parts | G14: 52.99 | H14: 45.04 | I14: 31.53 | J14: Each | L14: =K14*I14 -> 0
A15: 449582 | B15: 4-807 | C15: 12" Flat Box Seal | D15: =_xlfn.XLOOKUP(B15,'Product Hierarchy'!A:A,'Product Hierarchy'!C:C) -> LEVEL5 | E15: =_xlfn.XLOOKUP(B15,'Product Hierarchy'!A:A,'Product Hierarchy'!E:E) -> Drywall Auto Tools | F15: =_xlfn.XLOOKUP(B15,'Product Hierarchy'!A:A,'Product Hierarchy'!F:F) -> Repair Kits | G15: 60.49 | H15: 48.39 | I15: 33.87 | J15: Each | L15: =K15*I15 -> 0
A16: 449583 | B16: 4-808 | C16: Flat Box Repair Kit | D16: =_xlfn.XLOOKUP(B16,'Product Hierarchy'!A:A,'Product Hierarchy'!C:C) -> LEVEL5 | E16: =_xlfn.XLOOKUP(B16,'Product Hierarchy'!A:A,'Product Hierarchy'!E:E) -> Drywall Auto Tools | F16: =_xlfn.XLOOKUP(B16,'Product Hierarchy'!A:A,'Product Hierarchy'!F:F) -> Repair Kits | G16: 58.9 | H16: 47.12 | I16: 32.98 | J16: Each | L16: =K16*I16 -> 0
A17: 448547 | B17: 4-811 | C17: Cleaning Nozzles 2pk | D17: =_xlfn.XLOOKUP(B17,'Product Hierarchy'!A:A,'Product Hierarchy'!C:C) -> LEVEL5 | E17: =_xlfn.XLOOKUP(B17,'Product Hierarchy'!A:A,'Product Hierarchy'!E:E) -> Drywall Auto Tools | F17: =_xlfn.XLOOKUP(B17,'Product Hierarchy'!A:A,'Product Hierarchy'!F:F) -> Parts | G17: 27.98 | H17: 23.78 | I17: 16.65 | J17: Each | L17: =K17*I17 -> 0
A18: 448548 | B18: 4-812 | C18: Tape Jam Remover | D18: =_xlfn.XLOOKUP(B18,'Product Hierarchy'!A:A,'Product Hierarchy'!C:C) -> LEVEL5 | E18: =_xlfn.XLOOKUP(B18,'Product Hierarchy'!A:A,'Product Hierarchy'!E:E) -> Drywall Auto Tools | F18: =_xlfn.XLOOKUP(B18,'Product Hierarchy'!A:A,'Product Hierarchy'!F:F) -> Parts | G18: 18.49 | H18: 15.72 | I18: 11 | J18: Each | L18: =K18*I18 -> 0
A19: 448549 | B19: 4-813 | C19: Gooseneck Brush | D19: =_xlfn.XLOOKUP(B19,'Product Hierarchy'!A:A,'Product Hierarchy'!C:C) -> LEVEL5 | E19: =_xlfn.XLOOKUP(B19,'Product Hierarchy'!A:A,'Product Hierarchy'!E:E) -> Drywall Auto Tools | F19: =_xlfn.XLOOKUP(B19,'Product Hierarchy'!A:A,'Product Hierarchy'!F:F) -> Parts | G19: 52.99 | H19: 45.04 | I19: 31.53 | J19: Each | L19: =K19*I19 -> 0
A20: 449584 | B20: 4-815 | C20: Taper Repair Kit | D20: =_xlfn.XLOOKUP(B20,'Product Hierarchy'!A:A,'Product Hierarchy'!C:C) -> LEVEL5 | E20: =_xlfn.XLOOKUP(B20,'Product Hierarchy'!A:A,'Product Hierarchy'!E:E) -> Drywall Auto Tools | F20: =_xlfn.XLOOKUP(B20,'Product Hierarchy'!A:A,'Product Hierarchy'!F:F) -> Repair Kits | G20: 91.31 | H20: 73.05 | I20: 51.14 | J20: Each | L20: =K20*I20 -> 0
... A73: 449205 | B73: DXTT-2-807 | C73: DW 12"Flat Box Seal | D73: =_xlfn.XLOOKUP(B73,'Product Hierarchy'!A:A,'Product Hierarchy'!C:C) -> DEWALT | E73: =_xlfn.XLOOKUP(B73,'Product Hierarchy'!A:A,'Product Hierarchy'!E:E) -> Drywall Auto Tools | F73: =_xlfn.XLOOKUP(B73,'Product Hierarchy'!A:A,'Product Hierarchy'!F:F) -> Parts | G73: 60.49 | H73: 48.39 | I73: 33.87 | J73: Each | L73: =K73*I73 -> 0
J74: Total | K74: =SUM(K10:K73) -> 0 | L74: =SUM(L10:L73) -> 0

Sheet Order Input-Merch. And Mktg
F1: Order Form
A3: Customer: | B3: ='Order Summary'!B3 -> 0 | I3: Order date: | K3: ='Order Summary'!F3 -> 0
A4: Ship To: | B4: ='Order Summary'!B4 -> 0 | I4: PO#: | K4: ='Order Summary'!F4 -> 0
A5: ='Order Summary'!B5 -> 0 | I5: Need by date: | K5: ='Order Summary'!F5 -> 0
A6: ='Order Summary'!B6 -> 0 | I6: Carrier: | K6: ='Order Summary'!F6 -> 0
A7: ALL MERCH & MKTG SALES ARE FINAL
A8: Part # | B8: Sku # | C8: Description | D8: Brand | E8: Product Group | F8: Product Type | G8: MSRP | H8: MAPP | I8: Your Price | J8: UOM | K8: Order Quantity | L8: Total Price
A9: 449220 | B9: 1-120 | C9: L5T Baseball Cap | D9: =_xlfn.XLOOKUP(B9,'Product Hierarchy'!A:A,'Product Hierarchy'!C:C) -> LEVEL5 | E9: =_xlfn.XLOOKUP(B9,'Product Hierarchy'!A:A,'Product Hierarchy'!E:E) -> Misc | F9: =_xlfn.XLOOKUP(B9,'Product Hierarchy'!A:A,'Product Hierarchy'!F:F) -> Clothing | G9: 9.49 | H9: 8.54 | I9: 5.98 | J9: Each | L9: =K9*I9 -> 0
A10: 449239 | B10: 1-301 | C10: Safety Green T-Shirt Version 3 - Small | D10: =_xlfn.XLOOKUP(B10,'Product Hierarchy'!A:A,'Product Hierarchy'!C:C) -> LEVEL5 | E10: =_xlfn.XLOOKUP(B10,'Product Hierarchy'!A:A,'Product Hierarchy'!E:E) -> Misc | F10: =_xlfn.XLOOKUP(B10,'Product Hierarchy'!A:A,'Product Hierarchy'!F:F) -> Clothing | G10: 19.99 | H10: 17.99 | I10: 12.59 | J10: Each | L10: =K10*I10 -> 0
A11: 449240 | B11: 1-302 | C11: Safety Green T-Shirt Version 3 - Medium | D11: =_xlfn.XLOOKUP(B11,'Product Hierarchy'!A:A,'Product Hierarchy'!C:C) -> LEVEL5 | E11: =_xlfn.XLOOKUP(B11,'Product Hierarchy'!A:A,'Product Hierarchy'!E:E) -> Misc | F11: =_xlfn.XLOOKUP(B11,'Product Hierarchy'!A:A,'Product Hierarchy'!F:F) -> Clothing | G11: 19.99 | H11: 17.99 | I11: 12.59 | J11: Each | L11: =K11*I11 -> 0
A12: 449241 | B12: 1-303 | C12: Safety Green T-Shirt Version 3 - Large | D12: =_xlfn.XLOOKUP(B12,'Product Hierarchy'!A:A,'Product Hierarchy'!C:C) -> LEVEL5 | E12: =_xlfn.XLOOKUP(B12,'Product Hierarchy'!A:A,'Product Hierarchy'!E:E) -> Misc | F12: =_xlfn.XLOOKUP(B12,'Product Hierarchy'!A:A,'Product Hierarchy'!F:F) -> Clothing | G12: 19.99 | H12: 17.99 | I12: 12.59 | J12: Each | L12: =K12*I12 -> 0
A13: 449242 | B13: 1-304 | C13: Safety Green T-Shirt Version 3 - XL | D13: =_xlfn.XLOOKUP(B13,'Product Hierarchy'!A:A,'Product Hierarchy'!C:C) -> LEVEL5 | E13: =_xlfn.XLOOKUP(B13,'Product Hierarchy'!A:A,'Product Hierarchy'!E:E) -> Misc | F13: =_xlfn.XLOOKUP(B13,'Product Hierarchy'!A:A,'Product Hierarchy'!F:F) -> Clothing | G13: 19.99 | H13: 17.99 | I13: 12.59 | J13: Each | L13: =K13*I13 -> 0
A14: 449243 | B14: 1-305 | C14: Safety Green T-Shirt Version 3 - 2XL | D14: =_xlfn.XLOOKUP(B14,'Product Hierarchy'!A:A,'Product Hierarchy'!C:C) -> LEVEL5 | E14: =_xlfn.XLOOKUP(B14,'Product Hierarchy'!A:A,'Product Hierarchy'!E:E) -> Misc | F14: =_xlfn.XLOOKUP(B14,'Product Hierarchy'!A:A,'Product Hierarchy'!F:F) -> Clothing | G14: 19.99 | H14: 17.99 | I14: 12.59 | J14: Each | L14: =K14*I14 -> 0
A15: 449244 | B15: 1-306 | C15: Safety Green T-Shirt Version 3 - 3XL | D15: =_xlfn.XLOOKUP(B15,'Product Hierarchy'!A:A,'Product Hierarchy'!C:C) -> LEVEL5 | E15: =_xlfn.XLOOKUP(B15,'Product Hierarchy'!A:A,'Product Hierarchy'!E:E) -> Misc | F15: =_xlfn.XLOOKUP(B15,'Product Hierarchy'!A:A,'Product Hierarchy'!F:F) -> Clothing | G15: 19.99 | H15: 17.99 | I15: 12.59 | J15: Each | L15: =K15*I15 -> 0
A16: 449245 | B16: 1-311 | C16: Red T-Shirt Version 3 - Small | D16: =_xlfn.XLOOKUP(B16,'Product Hierarchy'!A:A,'Product Hierarchy'!C:C) -> LEVEL5 | E16: =_xlfn.XLOOKUP(B16,'Product Hierarchy'!A:A,'Product Hierarchy'!E:E) -> Misc | F16: =_xlfn.XLOOKUP(B16,'Product Hierarchy'!A:A,'Product Hierarchy'!F:F) -> Clothing | G16: 19.99 | H16: 17.99 | I16: 12.59 | J16: Each | L16: =K16*I16 -> 0
A17: 449246 | B17: 1-312 | C17: Red T-Shirt Version 3 - Medium | D17: =_xlfn.XLOOKUP(B17,'Product Hierarchy'!A:A,'Product Hierarchy'!C:C) -> LEVEL5 | E17: =_xlfn.XLOOKUP(B17,'Product Hierarchy'!A:A,'Product Hierarchy'!E:E) -> Misc | F17: =_xlfn.XLOOKUP(B17,'Product Hierarchy'!A:A,'Product Hierarchy'!F:F) -> Clothing | G17: 19.99 | H17: 17.99 | I17: 12.59 | J17: Each | L17: =K17*I17 -> 0
A18: 449247 | B18: 1-313 | C18: Red T-Shirt Version 3 - Large | D18: =_xlfn.XLOOKUP(B18,'Product Hierarchy'!A:A,'Product Hierarchy'!C:C) -> LEVEL5 | E18: =_xlfn.XLOOKUP(B18,'Product Hierarchy'!A:A,'Product Hierarchy'!E:E) -> Misc | F18: =_xlfn.XLOOKUP(B18,'Product Hierarchy'!A:A,'Product Hierarchy'!F:F) -> Clothing | G18: 19.99 | H18: 17.99 | I18: 12.59 | J18: Each | L18: =K18*I18 -> 0
A19: 449248 | B19: 1-314 | C19: Red T-Shirt Version 3 - XL | D19: =_xlfn.XLOOKUP(B19,'Product Hierarchy'!A:A,'Product Hierarchy'!C:C) -> LEVEL5 | E19: =_xlfn.XLOOKUP(B19,'Product Hierarchy'!A:A,'Product Hierarchy'!E:E) -> Misc | F19: =_xlfn.XLOOKUP(B19,'Product Hierarchy'!A:A,'Product Hierarchy'!F:F) -> Clothing | G19: 19.99 | H19: 17.99 | I19: 12.59 | J19: Each | L19: =K19*I19 -> 0
B20: 9-100 | C20: Brochure-DW Hand Tools | D20: =_xlfn.XLOOKUP(B20,'Product Hierarchy'!A:A,'Product Hierarchy'!C:C) -> DEWALT | E20: =_xlfn.XLOOKUP(B20,'Product Hierarchy'!A:A,'Product Hierarchy'!E:E) -> Misc | F20: =_xlfn.XLOOKUP(B20,'Product Hierarchy'!A:A,'Product Hierarchy'!F:F) -> Catalogs | G20: 0 | H20: 0 | I20: 0 | J20: Each | L20: =K20*I20 -> 0
B21: 9-101 | C21: Brochure-DW Automatic Taping Tools | D21: =_xlfn.XLOOKUP(B21,'Product Hierarchy'!A:A,'Product Hierarchy'!C:C) -> DEWALT | E21: =_xlfn.XLOOKUP(B21,'Product Hierarchy'!A:A,'Product Hierarchy'!E:E) -> Misc | F21: =_xlfn.XLOOKUP(B21,'Product Hierarchy'!A:A,'Product Hierarchy'!F:F) -> Catalogs | G21: 0 | H21: 0 | I21: 0 | J21: Each | L21: =K21*I21 -> 0
A22: 450981 | B22: 9-104 | C22: Brochure-L5 Hand Tools | D22: =_xlfn.XLOOKUP(B22,'Product Hierarchy'!A:A,'Product Hierarchy'!C:C) -> LEVEL5 | E22: =_xlfn.XLOOKUP(B22,'Product Hierarchy'!A:A,'Product Hierarchy'!E:E) -> Misc | F22: =_xlfn.XLOOKUP(B22,'Product Hierarchy'!A:A,'Product Hierarchy'!F:F) -> Catalogs | G22: 0 | H22: 0 | I22: 0 | J22: Each | L22: =K22*I22 -> 0
A23: 450982 | B23: 9-105 | C23: Brochure-L5 Automatic Taping Tools | D23: =_xlfn.XLOOKUP(B23,'Product Hierarchy'!A:A,'Product Hierarchy'!C:C) -> LEVEL5 | E23: =_xlfn.XLOOKUP(B23,'Product Hierarchy'!A:A,'Product Hierarchy'!E:E) -> Misc | F23: =_xlfn.XLOOKUP(B23,'Product Hierarchy'!A:A,'Product Hierarchy'!F:F) -> Catalogs | G23: 0 | H23: 0 | I23: 0 | J23: Each | L23: =K23*I23 -> 0
A24: 450983 | B24: 9-106 | C24: Brochure-L5 Skimming Blades | D24: =_xlfn.XLOOKUP(B24,'Product Hierarchy'!A:A,'Product Hierarchy'!C:C) -> LEVEL5 | E24: =_xlfn.XLOOKUP(B24,'Product Hierarchy'!A:A,'Product Hierarchy'!E:E) -> Misc | F24: =_xlfn.XLOOKUP(B24,'Product Hierarchy'!A:A,'Product Hierarchy'!F:F) -> Catalogs | G24: 0 | H24: 0 | I24: 0 | J24: Each | L24: =K24*I24 -> 0
J25: Merchandise and Marketing totals: | K25: =SUM(K9:K24) -> 0 | L25: =SUM(L9:L24) -> 0
